{"version":3,"kind":"Article","sha256":"ba912dcbb050a2dde4f3cb53dc1baf899de6e472b84888cca26be08530177b8f","slug":"index","location":"/index.md","dependencies":[],"frontmatter":{"title":"FAIRChem","site":{"hide_toc":true,"hide_outline":true,"hide_title_block":true},"authors":[{"nameParsed":{"literal":"FAIR Chemistry & Collaborators","given":"FAIR Chemistry &","family":"Collaborators"},"name":"FAIR Chemistry & Collaborators","id":"contributors-myst-generated-uid-0"}],"github":"https://github.com/facebookresearch/fairchem","copyright":"Meta Platforms, Inc","source_url":"https://github.com/facebookresearch/fairchem/blob/main/docs/index.md","edit_url":"https://github.com/facebookresearch/fairchem/edit/main/docs/index.md","thumbnail":"/build/fair_chem_logo_v2-da84111e8ea7347f72ba810d92f70d2e.png","exports":[{"format":"md","filename":"index.md","url":"/build/index-995617d5224ca8ca153b6847da4482a2.md"}]},"mdast":{"type":"root","children":[{"type":"block","position":{"start":{"line":9,"column":1},"end":{"line":9,"column":1}},"children":[{"type":"image","url":"/build/fair_chem_logo_v2-da84111e8ea7347f72ba810d92f70d2e.png","alt":"FAIRChem Logo","width":"600px","align":"center","key":"uqvil81f2N","urlSource":"assets/fair_chem_logo_v2.png"},{"type":"grid","columns":[1,2,2,2],"children":[{"type":"div","children":[{"type":"paragraph","position":{"start":{"line":19,"column":1},"end":{"line":19,"column":1}},"children":[{"type":"strong","position":{"start":{"line":19,"column":1},"end":{"line":19,"column":1}},"children":[{"type":"text","value":"Machine learning models for materials science and quantum chemistry.","position":{"start":{"line":19,"column":1},"end":{"line":19,"column":1}},"key":"XEkaBruqjI"}],"key":"FO2zfwnoNX"}],"key":"HbpOz2Ii3K"},{"type":"paragraph","position":{"start":{"line":21,"column":1},"end":{"line":21,"column":1}},"children":[{"type":"emphasis","position":{"start":{"line":21,"column":1},"end":{"line":21,"column":1}},"children":[{"type":"text","value":"State-of-the-art universal interatomic potentials for molecules, materials, and catalysts — built by the ","position":{"start":{"line":21,"column":1},"end":{"line":21,"column":1}},"key":"xQ9T3zB0og"},{"type":"link","url":"https://ai.meta.com/research/","position":{"start":{"line":21,"column":1},"end":{"line":21,"column":1}},"children":[{"type":"text","value":"Meta FAIR","position":{"start":{"line":21,"column":1},"end":{"line":21,"column":1}},"key":"WAwj17m7gn"}],"urlSource":"https://ai.meta.com/research/","key":"tbECygigse"},{"type":"text","value":" Chemistry team.","position":{"start":{"line":21,"column":1},"end":{"line":21,"column":1}},"key":"H7Xa1Fc4L2"}],"key":"NS8pgRrAGX"}],"key":"Hcjb4SGpEt"},{"type":"paragraph","children":[{"type":"link","url":"https://github.com/facebookresearch/fairchem/actions/workflows/test.yml","children":[{"type":"image","url":"/build/df5e84e4a108dd57527bc98b640f0a11.svg","alt":"tests","key":"zW0ZDTKdeG","urlSource":"https://github.com/facebookresearch/fairchem/actions/workflows/test.yml/badge.svg?branch=main"}],"urlSource":"https://github.com/facebookresearch/fairchem/actions/workflows/test.yml","error":true,"key":"TLh4JCI9bT"},{"type":"text","value":" ","key":"aIxpqbiUi1"},{"type":"link","url":"https://pypi.org/project/fairchem-core/","children":[{"type":"image","url":"/build/90729f84b60d98573e4d73413eda8c3c.svg","alt":"PyPI","key":"uNS6LgVu92","urlSource":"https://img.shields.io/pypi/v/fairchem-core"}],"urlSource":"https://pypi.org/project/fairchem-core/","key":"rGB76b3CcQ"},{"type":"text","value":" ","key":"V3cOPMCGj8"},{"type":"image","url":"/build/7b564561b4a824b749631c1d88a17f6b.svg","alt":"Python 3.10+","key":"Lruj2rPlrC","urlSource":"https://img.shields.io/badge/python-3.10%2B-blue"}],"key":"MBAgH8EziQ"}],"key":"dUcixoDABC"},{"type":"div","children":[{"type":"code","lang":"bash","filename":"install","value":"pip install fairchem-core","key":"mWBPbkNthC"},{"type":"paragraph","position":{"start":{"line":36,"column":1},"end":{"line":36,"column":1}},"children":[{"type":"link","url":"/quickstart","children":[{"type":"text","value":"Get Started →","key":"DlDueeOmlh"}],"class":"button","urlSource":"./core/quickstart.md","dataUrl":"/quickstart.json","internal":true,"protocol":"file","key":"ew0IRjjo3F"},{"type":"text","value":" ","position":{"start":{"line":36,"column":1},"end":{"line":36,"column":1}},"key":"XsGTP54NVL"},{"type":"link","url":"https://facebook-fairchem-uma-demo.hf.space/","children":[{"type":"text","value":"Try the Demo →","key":"bmt0VdQkMh"}],"class":"button","urlSource":"https://facebook-fairchem-uma-demo.hf.space/","key":"aelfkmlrVQ"}],"key":"h40thewWuy"}],"key":"hOMVZv4Rwi"}],"key":"cNgsKOw4rW"}],"class":"col-page-inset","key":"QcjNUwo4Pm"},{"type":"block","position":{"start":{"line":44,"column":1},"end":{"line":44,"column":1}},"children":[{"type":"heading","depth":2,"position":{"start":{"line":46,"column":1},"end":{"line":46,"column":1}},"children":[{"type":"text","value":"Application Domains","position":{"start":{"line":46,"column":1},"end":{"line":46,"column":1}},"key":"JwlZYOVcBS"}],"identifier":"application-domains","label":"Application Domains","html_id":"application-domains","implicit":true,"key":"p0wLM1eXD4"},{"type":"grid","columns":[1,2,3,5],"children":[{"type":"card","url":"/summary-3","children":[{"type":"cardTitle","children":[{"type":"text","value":"Heterogeneous Catalysis","position":{"start":{"line":49,"column":1},"end":{"line":49,"column":1}},"key":"DP89oXsRrB"}],"key":"woABOVhw2j"},{"type":"image","url":"/build/catalysis-6974df650ba1ad50cd5f40abf192559a.svg","alt":"Catalysis","width":"60px","align":"center","key":"MNv5ykOcud","urlSource":"assets/icons/catalysis.svg"},{"type":"paragraph","position":{"start":{"line":58,"column":1},"end":{"line":58,"column":1}},"children":[{"type":"text","value":"Surface reactions, adsorption energies, and catalyst design.","position":{"start":{"line":58,"column":1},"end":{"line":58,"column":1}},"key":"qyLQtk20Sc"}],"key":"BrqWDoKZsh"},{"type":"footer","children":[{"type":"paragraph","position":{"start":{"line":60,"column":1},"end":{"line":60,"column":1}},"children":[{"type":"link","url":"/summary-3","position":{"start":{"line":60,"column":1},"end":{"line":60,"column":1}},"children":[{"type":"text","value":"Explore Catalysis →","position":{"start":{"line":60,"column":1},"end":{"line":60,"column":1}},"key":"s5FNrTFng0"}],"urlSource":"catalysts/datasets/summary.md","dataUrl":"/summary-3.json","internal":true,"protocol":"file","key":"Anra2bfpWc"}],"key":"Xsji72Vvc3"}],"key":"sFVqrbmSHJ"}],"urlSource":"catalysts/datasets/summary.md","dataUrl":"/summary-3.json","internal":true,"protocol":"file","key":"CT6SUjmg1P"},{"type":"card","url":"/summary-5","children":[{"type":"cardTitle","children":[{"type":"text","value":"Inorganic Materials","position":{"start":{"line":63,"column":1},"end":{"line":63,"column":1}},"key":"eCr1KDujzd"}],"key":"jgbeGVfRVw"},{"type":"image","url":"/build/inorganic-db8366de9e82eba9a985b88aeaa71b6a.svg","alt":"Inorganic Materials","width":"60px","align":"center","key":"nDWvYqLKMb","urlSource":"assets/icons/inorganic.svg"},{"type":"paragraph","position":{"start":{"line":72,"column":1},"end":{"line":72,"column":1}},"children":[{"type":"text","value":"Bulk materials, phonons, and elastic properties.","position":{"start":{"line":72,"column":1},"end":{"line":72,"column":1}},"key":"VA4Om0jOHc"}],"key":"yRawwyOM04"},{"type":"footer","children":[{"type":"paragraph","position":{"start":{"line":74,"column":1},"end":{"line":74,"column":1}},"children":[{"type":"link","url":"/summary-5","position":{"start":{"line":74,"column":1},"end":{"line":74,"column":1}},"children":[{"type":"text","value":"Explore Materials →","position":{"start":{"line":74,"column":1},"end":{"line":74,"column":1}},"key":"j2BvqTE5Bb"}],"urlSource":"inorganic_materials/datasets/summary.md","dataUrl":"/summary-5.json","internal":true,"protocol":"file","key":"QHjUNKdyjH"}],"key":"Kev3q87qAV"}],"key":"sG4fO4ZLYw"}],"urlSource":"inorganic_materials/datasets/summary.md","dataUrl":"/summary-5.json","internal":true,"protocol":"file","key":"Ahr6UOhceR"},{"type":"card","url":"/summary-2","children":[{"type":"cardTitle","children":[{"type":"text","value":"Molecules & Polymers","position":{"start":{"line":77,"column":1},"end":{"line":77,"column":1}},"key":"HFTtI88L6E"}],"key":"Wbkau5mOHS"},{"type":"image","url":"/build/molecules-57efb863cc91a4e377548fc54a74debc.svg","alt":"Molecules & Polymers","width":"60px","align":"center","key":"Ela83y6bT1","urlSource":"assets/icons/molecules.svg"},{"type":"paragraph","position":{"start":{"line":86,"column":1},"end":{"line":86,"column":1}},"children":[{"type":"text","value":"Molecular conformers and electronic properties.","position":{"start":{"line":86,"column":1},"end":{"line":86,"column":1}},"key":"gHUqG9BixO"}],"key":"dfXd4TS32d"},{"type":"footer","children":[{"type":"paragraph","position":{"start":{"line":88,"column":1},"end":{"line":88,"column":1}},"children":[{"type":"link","url":"/summary-2","position":{"start":{"line":88,"column":1},"end":{"line":88,"column":1}},"children":[{"type":"text","value":"Explore Molecules →","position":{"start":{"line":88,"column":1},"end":{"line":88,"column":1}},"key":"PMg5bNNDq1"}],"urlSource":"molecules/datasets/summary.md","dataUrl":"/summary-2.json","internal":true,"protocol":"file","key":"vUfaJryE1Z"}],"key":"WUYxTLiT5Q"}],"key":"s8GMbLDsqM"}],"urlSource":"molecules/datasets/summary.md","dataUrl":"/summary-2.json","internal":true,"protocol":"file","key":"ToB7VltQps"},{"type":"card","url":"/omc25","children":[{"type":"cardTitle","children":[{"type":"text","value":"Molecular Crystals","position":{"start":{"line":91,"column":1},"end":{"line":91,"column":1}},"key":"EuZQwtkQfz"}],"key":"hGaZ8BZ1jL"},{"type":"image","url":"/build/molecular-crystals-d3c766f14275cef01b2aca53cb42bb2b.svg","alt":"Molecular Crystals","width":"60px","align":"center","key":"Iv5vBrtaJF","urlSource":"assets/icons/molecular-crystals.svg"},{"type":"paragraph","position":{"start":{"line":100,"column":1},"end":{"line":100,"column":1}},"children":[{"type":"text","value":"Packed molecular arrangements in crystal structures.","position":{"start":{"line":100,"column":1},"end":{"line":100,"column":1}},"key":"YqdWTffwHM"}],"key":"k5HIMbYG6N"},{"type":"footer","children":[{"type":"paragraph","position":{"start":{"line":102,"column":1},"end":{"line":102,"column":1}},"children":[{"type":"link","url":"/omc25","position":{"start":{"line":102,"column":1},"end":{"line":102,"column":1}},"children":[{"type":"text","value":"Explore Crystals →","position":{"start":{"line":102,"column":1},"end":{"line":102,"column":1}},"key":"B7iOD3qIwn"}],"urlSource":"molecules/datasets/omc25.md","dataUrl":"/omc25.json","internal":true,"protocol":"file","key":"sKNBdYFSvN"}],"key":"k78hMIHTnM"}],"key":"oZK5EWgt0y"}],"urlSource":"molecules/datasets/omc25.md","dataUrl":"/omc25.json","internal":true,"protocol":"file","key":"SD58UWwHLJ"},{"type":"card","url":"/summary-7","children":[{"type":"cardTitle","children":[{"type":"text","value":"MOFs for Direct Air Capture","position":{"start":{"line":105,"column":1},"end":{"line":105,"column":1}},"key":"yqZdgoK4wA"}],"key":"hnViQAaHSO"},{"type":"image","url":"/build/mofs-dac-243bdaafe495a626ed8183ca91543cab.svg","alt":"MOFs for DAC","width":"60px","align":"center","key":"FfQwpA18Ar","urlSource":"assets/icons/mofs-dac.svg"},{"type":"paragraph","position":{"start":{"line":114,"column":1},"end":{"line":114,"column":1}},"children":[{"type":"text","value":"Metal-organic frameworks for CO₂ capture.","position":{"start":{"line":114,"column":1},"end":{"line":114,"column":1}},"key":"BD45M48DgT"}],"key":"rreQtkWalN"},{"type":"footer","children":[{"type":"paragraph","position":{"start":{"line":116,"column":1},"end":{"line":116,"column":1}},"children":[{"type":"link","url":"/summary-7","position":{"start":{"line":116,"column":1},"end":{"line":116,"column":1}},"children":[{"type":"text","value":"Explore DAC →","position":{"start":{"line":116,"column":1},"end":{"line":116,"column":1}},"key":"TxMVFiW8ob"}],"urlSource":"dac/datasets/summary.md","dataUrl":"/summary-7.json","internal":true,"protocol":"file","key":"OAGnntfXh1"}],"key":"d2oCSif2eQ"}],"key":"UPOhL88mNn"}],"urlSource":"dac/datasets/summary.md","dataUrl":"/summary-7.json","internal":true,"protocol":"file","key":"Jrbk1MnnQQ"}],"key":"bHTG4vCrGt"}],"kind":"justified","key":"KL2gBbqAx7"},{"type":"block","position":{"start":{"line":120,"column":1},"end":{"line":120,"column":1}},"children":[{"type":"heading","depth":2,"position":{"start":{"line":122,"column":1},"end":{"line":122,"column":1}},"children":[{"type":"text","value":"Get Started","position":{"start":{"line":122,"column":1},"end":{"line":122,"column":1}},"key":"OEmLtulqJh"}],"identifier":"get-started","label":"Get Started","html_id":"get-started","implicit":true,"key":"KHa4j0lIJX"},{"type":"grid","columns":[1,2,3,3],"children":[{"type":"card","url":"/quickstart","children":[{"type":"cardTitle","children":[{"type":"text","value":"📘 Quickstart","position":{"start":{"line":125,"column":1},"end":{"line":125,"column":1}},"key":"RrHL2hdh5t"}],"key":"XpsEtDcxOD"},{"type":"paragraph","position":{"start":{"line":128,"column":1},"end":{"line":128,"column":1}},"children":[{"type":"text","value":"Build your first calculation in minutes","position":{"start":{"line":128,"column":1},"end":{"line":128,"column":1}},"key":"cSYqRlTrAS"}],"key":"hRGKxyi61G"},{"type":"footer","children":[{"type":"paragraph","position":{"start":{"line":130,"column":1},"end":{"line":130,"column":1}},"children":[{"type":"link","url":"/quickstart","position":{"start":{"line":130,"column":1},"end":{"line":130,"column":1}},"children":[{"type":"text","value":"Start now →","position":{"start":{"line":130,"column":1},"end":{"line":130,"column":1}},"key":"wihJaF9eNM"}],"urlSource":"./core/quickstart.md","dataUrl":"/quickstart.json","internal":true,"protocol":"file","key":"ZpOt8sNaeF"}],"key":"BnHL9yTJ7e"}],"key":"dRcefn4O2y"}],"urlSource":"./core/quickstart.md","dataUrl":"/quickstart.json","internal":true,"protocol":"file","key":"CF53XNLrb7"},{"type":"card","url":"/uma","children":[{"type":"cardTitle","children":[{"type":"text","value":"📖 UMA Model Guide","position":{"start":{"line":133,"column":1},"end":{"line":133,"column":1}},"key":"PQ82TLHkoU"}],"key":"qboAZSskGE"},{"type":"paragraph","position":{"start":{"line":136,"column":1},"end":{"line":136,"column":1}},"children":[{"type":"text","value":"Learn about task selection and model inputs","position":{"start":{"line":136,"column":1},"end":{"line":136,"column":1}},"key":"AEXhto1CL9"}],"key":"D0QAQhwYb8"},{"type":"footer","children":[{"type":"paragraph","position":{"start":{"line":138,"column":1},"end":{"line":138,"column":1}},"children":[{"type":"link","url":"/uma","position":{"start":{"line":138,"column":1},"end":{"line":138,"column":1}},"children":[{"type":"text","value":"Read guide →","position":{"start":{"line":138,"column":1},"end":{"line":138,"column":1}},"key":"oaaYbJeZKL"}],"urlSource":"./core/uma.md","dataUrl":"/uma.json","internal":true,"protocol":"file","key":"IP6PaK3fvd"}],"key":"AQ2oudfHxr"}],"key":"dVnPpJD70A"}],"urlSource":"./core/uma.md","dataUrl":"/uma.json","internal":true,"protocol":"file","key":"vdVAMel28I"},{"type":"card","url":"/install","children":[{"type":"cardTitle","children":[{"type":"text","value":"🔧 Installation","position":{"start":{"line":141,"column":1},"end":{"line":141,"column":1}},"key":"ArKsCzU2Yf"}],"key":"naUcMwNiB7"},{"type":"paragraph","position":{"start":{"line":144,"column":1},"end":{"line":144,"column":1}},"children":[{"type":"text","value":"Set up FAIRChem and HuggingFace access","position":{"start":{"line":144,"column":1},"end":{"line":144,"column":1}},"key":"oU0jvFvV5i"}],"key":"iWHp5SZkBu"},{"type":"footer","children":[{"type":"paragraph","position":{"start":{"line":146,"column":1},"end":{"line":146,"column":1}},"children":[{"type":"link","url":"/install","position":{"start":{"line":146,"column":1},"end":{"line":146,"column":1}},"children":[{"type":"text","value":"Install →","position":{"start":{"line":146,"column":1},"end":{"line":146,"column":1}},"key":"kC3ICJrme9"}],"urlSource":"./core/install.md","dataUrl":"/install.json","internal":true,"protocol":"file","key":"jpPFRnlK3r"}],"key":"YsAm06zFZN"}],"key":"hYVWFtvNOt"}],"urlSource":"./core/install.md","dataUrl":"/install.json","internal":true,"protocol":"file","key":"cTQLbbDjMs"},{"type":"card","url":"/summary-1","children":[{"type":"cardTitle","children":[{"type":"text","value":"🎓 Tutorials","position":{"start":{"line":149,"column":1},"end":{"line":149,"column":1}},"key":"sajOQP9PiT"}],"key":"UHJ6ngVWUi"},{"type":"paragraph","position":{"start":{"line":152,"column":1},"end":{"line":152,"column":1}},"children":[{"type":"text","value":"Hands-on tutorials for common workflows","position":{"start":{"line":152,"column":1},"end":{"line":152,"column":1}},"key":"EDbbFvDlfp"}],"key":"CPzyoKKFYN"},{"type":"footer","children":[{"type":"paragraph","position":{"start":{"line":154,"column":1},"end":{"line":154,"column":1}},"children":[{"type":"link","url":"/summary-1","position":{"start":{"line":154,"column":1},"end":{"line":154,"column":1}},"children":[{"type":"text","value":"View tutorials →","position":{"start":{"line":154,"column":1},"end":{"line":154,"column":1}},"key":"RC8lQRffnf"}],"urlSource":"./uma_tutorials/summary.md","dataUrl":"/summary-1.json","internal":true,"protocol":"file","key":"R2O9eLeyRs"}],"key":"Lt8QMeE8aZ"}],"key":"JyaT4CD5jV"}],"urlSource":"./uma_tutorials/summary.md","dataUrl":"/summary-1.json","internal":true,"protocol":"file","key":"aO752vuabR"},{"type":"card","url":"/summary","children":[{"type":"cardTitle","children":[{"type":"text","value":"📊 Common Tasks","position":{"start":{"line":157,"column":1},"end":{"line":157,"column":1}},"key":"aPhH8VzQYU"}],"key":"ZBJ6y6cvcM"},{"type":"paragraph","position":{"start":{"line":160,"column":1},"end":{"line":160,"column":1}},"children":[{"type":"text","value":"Inference, training, fine-tuning, and more","position":{"start":{"line":160,"column":1},"end":{"line":160,"column":1}},"key":"MrVO5AecSx"}],"key":"aT7xpsYUU8"},{"type":"footer","children":[{"type":"paragraph","position":{"start":{"line":162,"column":1},"end":{"line":162,"column":1}},"children":[{"type":"link","url":"/summary","position":{"start":{"line":162,"column":1},"end":{"line":162,"column":1}},"children":[{"type":"text","value":"Browse tasks →","position":{"start":{"line":162,"column":1},"end":{"line":162,"column":1}},"key":"QhLwHp2N7z"}],"urlSource":"./core/common_tasks/summary.md","dataUrl":"/summary.json","internal":true,"protocol":"file","key":"kYV4Hzm4eI"}],"key":"aYmODgwrkW"}],"key":"woTKeUpjAP"}],"urlSource":"./core/common_tasks/summary.md","dataUrl":"/summary.json","internal":true,"protocol":"file","key":"HkVvVFVdIN"},{"type":"card","url":"/technical-talks","children":[{"type":"cardTitle","children":[{"type":"text","value":"🎬 Technical Talks","position":{"start":{"line":165,"column":1},"end":{"line":165,"column":1}},"key":"KaSJ4w8ggF"}],"key":"Zaf3x8g18y"},{"type":"paragraph","position":{"start":{"line":168,"column":1},"end":{"line":168,"column":1}},"children":[{"type":"text","value":"Video presentations from the team","position":{"start":{"line":168,"column":1},"end":{"line":168,"column":1}},"key":"gdLiSIHmMR"}],"key":"t7pEalPhV3"},{"type":"footer","children":[{"type":"paragraph","position":{"start":{"line":170,"column":1},"end":{"line":170,"column":1}},"children":[{"type":"link","url":"/technical-talks","position":{"start":{"line":170,"column":1},"end":{"line":170,"column":1}},"children":[{"type":"text","value":"Watch →","position":{"start":{"line":170,"column":1},"end":{"line":170,"column":1}},"key":"J1xRwunn9E"}],"urlSource":"./videos/technical_talks.md","dataUrl":"/technical-talks.json","internal":true,"protocol":"file","key":"BapKPTu5yw"}],"key":"hkxrhKD2hN"}],"key":"ahOcJPyUuf"}],"urlSource":"./videos/technical_talks.md","dataUrl":"/technical-talks.json","internal":true,"protocol":"file","key":"mkueGRVF9R"}],"key":"Zz1C6NWgoC"}],"kind":"justified","key":"WzyPqFUSgs"},{"type":"block","position":{"start":{"line":174,"column":1},"end":{"line":174,"column":1}},"children":[{"type":"heading","depth":2,"position":{"start":{"line":176,"column":1},"end":{"line":176,"column":1}},"children":[{"type":"text","value":"The UMA Model","position":{"start":{"line":176,"column":1},"end":{"line":176,"column":1}},"key":"y4whOKtiab"}],"identifier":"the-uma-model","label":"The UMA Model","html_id":"the-uma-model","implicit":true,"key":"geZg9og7r2"},{"type":"paragraph","position":{"start":{"line":178,"column":1},"end":{"line":178,"column":1}},"children":[{"type":"text","value":"Read about our latest release: the ","position":{"start":{"line":178,"column":1},"end":{"line":178,"column":1}},"key":"goYLDDGMWS"},{"type":"strong","position":{"start":{"line":178,"column":1},"end":{"line":178,"column":1}},"children":[{"type":"text","value":"Universal Machine-learning for Atomistic systems (UMA)","position":{"start":{"line":178,"column":1},"end":{"line":178,"column":1}},"key":"Bk6ZZx6H9g"}],"key":"db3s69aRVE"},{"type":"text","value":" model.","position":{"start":{"line":178,"column":1},"end":{"line":178,"column":1}},"key":"rizPweacIl"}],"key":"y61xsdh3DG"},{"type":"card","url":"https://ai.meta.com/blog/meta-fair-science-new-open-source-releases/","children":[{"type":"cardTitle","children":[{"type":"text","value":"Meta FAIR Science Release","position":{"start":{"line":180,"column":1},"end":{"line":180,"column":1}},"key":"s1pEA8q3cV"}],"key":"yHeFkwu83c"},{"type":"image","url":"/build/9f9e0b8a69b7eb4407ae16c1e1adc129.png","alt":"Meta FAIR Science Release","width":"100%","align":"center","key":"gsCR9dVA77","urlSource":"https://github.com/user-attachments/assets/acddd09b-ed6f-4d05-9a4b-9ba5e2301150"},{"type":"paragraph","position":{"start":{"line":188,"column":1},"end":{"line":188,"column":1}},"children":[{"type":"text","value":"UMA is trained on 500M+ DFT calculations across molecules, materials, and catalysts — achieving state-of-the-art accuracy with energy conservation and fast inference.","position":{"start":{"line":188,"column":1},"end":{"line":188,"column":1}},"key":"WHNcMrhO2D"}],"key":"hZPK1nVOh8"}],"urlSource":"https://ai.meta.com/blog/meta-fair-science-new-open-source-releases/","key":"u2rU7gPz4h"},{"type":"admonition","kind":"attention","children":[{"type":"admonitionTitle","children":[{"type":"text","value":"FAIRChem v2 is here!","position":{"start":{"line":191,"column":1},"end":{"line":191,"column":1}},"key":"kClKYsiE3A"}],"key":"PFj5vw7HJf"},{"type":"paragraph","position":{"start":{"line":192,"column":1},"end":{"line":193,"column":1}},"children":[{"type":"text","value":"FAIRChem v2 introduces the ","position":{"start":{"line":192,"column":1},"end":{"line":192,"column":1}},"key":"Lokarf97w4"},{"type":"strong","position":{"start":{"line":192,"column":1},"end":{"line":192,"column":1}},"children":[{"type":"text","value":"UMA model","position":{"start":{"line":192,"column":1},"end":{"line":192,"column":1}},"key":"Lmw5KuEREm"}],"key":"TdTZmV9x8H"},{"type":"text","value":" — a universal machine learning potential for atoms.\nThis is a breaking change from v1 and is not compatible with previous pretrained models.","position":{"start":{"line":192,"column":1},"end":{"line":192,"column":1}},"key":"UO2vRM1f6V"}],"key":"mxE6zYms47"},{"type":"paragraph","position":{"start":{"line":195,"column":1},"end":{"line":195,"column":1}},"children":[{"type":"link","url":"/fairchemv1-v2","position":{"start":{"line":195,"column":1},"end":{"line":195,"column":1}},"children":[{"type":"text","value":"Migration Guide","position":{"start":{"line":195,"column":1},"end":{"line":195,"column":1}},"key":"rNa87AqzNV"}],"urlSource":"core/fairchemv1_v2.md","dataUrl":"/fairchemv1-v2.json","internal":true,"protocol":"file","key":"uIRGklxdpg"},{"type":"text","value":" • ","position":{"start":{"line":195,"column":1},"end":{"line":195,"column":1}},"key":"lk8b3m8mGx"},{"type":"link","url":"https://pypi.org/project/fairchem-core/1.10.0/","position":{"start":{"line":195,"column":1},"end":{"line":195,"column":1}},"children":[{"type":"text","value":"Version 1 Documentation","position":{"start":{"line":195,"column":1},"end":{"line":195,"column":1}},"key":"l6qzMoKwkV"}],"urlSource":"https://pypi.org/project/fairchem-core/1.10.0/","key":"S9iN1OS3VX"}],"key":"NQpxYjjwVK"}],"key":"gWxWxLrxMu"}],"kind":"justified","key":"vAIFE1oQIK"},{"type":"block","position":{"start":{"line":198,"column":1},"end":{"line":198,"column":1}},"children":[{"type":"heading","depth":2,"position":{"start":{"line":200,"column":1},"end":{"line":200,"column":1}},"children":[{"type":"text","value":"Resources","position":{"start":{"line":200,"column":1},"end":{"line":200,"column":1}},"key":"gYlCMYepSL"}],"identifier":"resources","label":"Resources","html_id":"resources","implicit":true,"key":"cDOW8Go8Le"},{"type":"grid","columns":[1,1,2,2],"children":[{"type":"card","url":"https://github.com/facebookresearch/fairchem","children":[{"type":"cardTitle","children":[{"type":"text","value":"GitHub Repository","position":{"start":{"line":203,"column":1},"end":{"line":203,"column":1}},"key":"lQ6ySlVhHD"}],"key":"Cihik8f2QZ"},{"type":"paragraph","position":{"start":{"line":206,"column":1},"end":{"line":206,"column":1}},"children":[{"type":"text","value":"Browse source code, report issues, and contribute","position":{"start":{"line":206,"column":1},"end":{"line":206,"column":1}},"key":"q6e4wom3zw"}],"key":"uBKTqajsN0"},{"type":"footer","children":[{"type":"paragraph","position":{"start":{"line":208,"column":1},"end":{"line":208,"column":1}},"children":[{"type":"link","url":"https://github.com/facebookresearch/fairchem","position":{"start":{"line":208,"column":1},"end":{"line":208,"column":1}},"children":[{"type":"text","value":"facebookresearch​/fairchem","position":{"start":{"line":208,"column":1},"end":{"line":208,"column":1}},"key":"lk0Dqebkqn"}],"urlSource":"https://github.com/facebookresearch/fairchem","error":true,"key":"wxMcH4K3Yq"}],"key":"yjaT7iIO9a"}],"key":"qkwJBgeg9L"}],"urlSource":"https://github.com/facebookresearch/fairchem","error":true,"key":"xRFuslSKMW"},{"type":"card","url":"./core/papers_using_models.md","children":[{"type":"cardTitle","children":[{"type":"text","value":"Papers Using FAIRChem","position":{"start":{"line":211,"column":1},"end":{"line":211,"column":1}},"key":"XAsSwjhmjv"}],"key":"nmUC39GOeY"},{"type":"paragraph","position":{"start":{"line":214,"column":1},"end":{"line":214,"column":1}},"children":[{"type":"text","value":"See how researchers are using our models","position":{"start":{"line":214,"column":1},"end":{"line":214,"column":1}},"key":"Pmimq75eUl"}],"key":"mZK1sL3y9P"},{"type":"footer","children":[{"type":"paragraph","position":{"start":{"line":216,"column":1},"end":{"line":216,"column":1}},"children":[{"type":"link","url":"./core/papers_using_models.md","position":{"start":{"line":216,"column":1},"end":{"line":216,"column":1}},"children":[{"type":"text","value":"View publications →","position":{"start":{"line":216,"column":1},"end":{"line":216,"column":1}},"key":"FATs8FIQyk"}],"urlSource":"./core/papers_using_models.md","key":"BNpvn16UcK"}],"key":"V88BV7gmm3"}],"key":"J8qhdViKuK"}],"urlSource":"./core/papers_using_models.md","key":"fnrJ9TM921"},{"type":"card","url":"https://github.com/codespaces/new/facebookresearch/fairchem?quickstart=1","children":[{"type":"cardTitle","children":[{"type":"text","value":"Open in Codespaces","position":{"start":{"line":219,"column":1},"end":{"line":219,"column":1}},"key":"IicihHIJ9l"}],"key":"zqGPwt2CjX"},{"type":"paragraph","position":{"start":{"line":222,"column":1},"end":{"line":222,"column":1}},"children":[{"type":"text","value":"Try FAIRChem in your browser — no local setup required","position":{"start":{"line":222,"column":1},"end":{"line":222,"column":1}},"key":"b2V4lVAsPi"}],"key":"tDQ6K9aVVD"},{"type":"footer","children":[{"type":"paragraph","position":{"start":{"line":224,"column":1},"end":{"line":224,"column":1}},"children":[{"type":"link","url":"https://github.com/codespaces/new/facebookresearch/fairchem?quickstart=1","position":{"start":{"line":224,"column":1},"end":{"line":224,"column":1}},"children":[{"type":"image","url":"/build/f64bfceadefc97b376485eaeb63a6675.svg","alt":"Open in GitHub Codespaces","position":{"start":{"line":224,"column":1},"end":{"line":224,"column":1}},"key":"emxRGzelJ5","urlSource":"https://github.com/codespaces/badge.svg"}],"urlSource":"https://github.com/codespaces/new/facebookresearch/fairchem?quickstart=1","error":true,"key":"cA2lqTeJqp"}],"key":"LojvbyT5sQ"}],"key":"vKaIQEvs06"}],"urlSource":"https://github.com/codespaces/new/facebookresearch/fairchem?quickstart=1","error":true,"key":"XG1k7ef9Mm"},{"type":"card","url":"https://huggingface.co/facebook/UMA","children":[{"type":"cardTitle","children":[{"type":"text","value":"HuggingFace Models","position":{"start":{"line":227,"column":1},"end":{"line":227,"column":1}},"key":"tCZJj4lj5X"}],"key":"SXvLplr7na"},{"type":"paragraph","position":{"start":{"line":230,"column":1},"end":{"line":230,"column":1}},"children":[{"type":"text","value":"Access pretrained UMA checkpoints","position":{"start":{"line":230,"column":1},"end":{"line":230,"column":1}},"key":"rA7iQapNQf"}],"key":"q7NJzTmZd6"},{"type":"footer","children":[{"type":"paragraph","position":{"start":{"line":232,"column":1},"end":{"line":232,"column":1}},"children":[{"type":"link","url":"https://huggingface.co/facebook/UMA","position":{"start":{"line":232,"column":1},"end":{"line":232,"column":1}},"children":[{"type":"text","value":"facebook/UMA","position":{"start":{"line":232,"column":1},"end":{"line":232,"column":1}},"key":"o2UN1WsCTg"}],"urlSource":"https://huggingface.co/facebook/UMA","key":"EiUWIDPU6l"}],"key":"qOI07rYyMa"}],"key":"bEFKbBs88R"}],"urlSource":"https://huggingface.co/facebook/UMA","key":"o39ZFa0ea5"}],"key":"aRB17ieS7I"}],"kind":"justified","key":"PB5OvDtYRy"}],"key":"WdfwoMT0rN"},"references":{"cite":{"order":[],"data":{}}},"footer":{"navigation":{"next":{"title":"Installation & License","url":"/install","group":"Quickstart"}}},"domain":"http://localhost:3000"}