{"version":3,"kind":"Article","sha256":"14c3bf15ca75839551d285eb3dcc8f07ca1c29663b00b9a4c98faf72f74e32ee","slug":"odac23","location":"/dac/datasets/odac23.md","dependencies":[],"frontmatter":{"title":"Open Direct Air Capture 2023 (ODAC23)","content_includes_title":false,"authors":[{"nameParsed":{"literal":"FAIR Chemistry & Collaborators","given":"FAIR Chemistry &","family":"Collaborators"},"name":"FAIR Chemistry & Collaborators","id":"contributors-myst-generated-uid-0"}],"github":"https://github.com/facebookresearch/fairchem","copyright":"Meta Platforms, Inc","numbering":{"title":{"offset":2}},"source_url":"https://github.com/facebookresearch/fairchem/blob/main/docs/dac/datasets/odac23.md","edit_url":"https://github.com/facebookresearch/fairchem/edit/main/docs/dac/datasets/odac23.md","exports":[{"format":"md","filename":"odac23.md","url":"/build/odac23-242d02287ccd3b6093bfbe875cd68980.md"}]},"mdast":{"type":"root","children":[{"type":"block","children":[{"type":"admonition","kind":"warning","children":[{"type":"admonitionTitle","children":[{"type":"text","value":"Warning","key":"DoSCOB55zO"}],"key":"SNIB1lkHfm"},{"type":"paragraph","position":{"start":{"line":5,"column":1},"end":{"line":5,"column":1}},"children":[{"type":"strong","position":{"start":{"line":5,"column":1},"end":{"line":5,"column":1}},"children":[{"type":"text","value":"Deprecated","position":{"start":{"line":5,"column":1},"end":{"line":5,"column":1}},"key":"U2nHA5oxCV"}],"key":"scFl5Y1WRI"},{"type":"text","value":": ODAC23 has been superseded by ","position":{"start":{"line":5,"column":1},"end":{"line":5,"column":1}},"key":"eafF9USiyw"},{"type":"link","url":"/odac25","position":{"start":{"line":5,"column":1},"end":{"line":5,"column":1}},"children":[{"type":"text","value":"ODAC25","position":{"start":{"line":5,"column":1},"end":{"line":5,"column":1}},"key":"VRRONp1gnd"}],"urlSource":"odac25.md","dataUrl":"/odac25.json","internal":true,"protocol":"file","key":"m3m5RUB75H"},{"type":"text","value":", which contains nearly 70 million DFT calculations across 4 adsorbates (CO2, H2O, N2, O2) in nearly 15,000 MOFs. We recommend using ODAC25 for new projects.","position":{"start":{"line":5,"column":1},"end":{"line":5,"column":1}},"key":"VaZrke4uCi"}],"key":"QWw2QYm5Mu"}],"key":"lLc1KDmruL"},{"type":"card","children":[{"type":"cardTitle","children":[{"type":"text","value":"Dataset Overview","position":{"start":{"line":8,"column":1},"end":{"line":8,"column":1}},"key":"o64AWecHkk"}],"key":"EaHeYyQdIB"},{"type":"table","position":{"start":{"line":10,"column":1},"end":{"line":17,"column":1}},"children":[{"type":"tableRow","position":{"start":{"line":10,"column":1},"end":{"line":10,"column":1}},"children":[{"type":"tableCell","header":true,"position":{"start":{"line":10,"column":1},"end":{"line":10,"column":1}},"children":[{"type":"text","value":"Property","position":{"start":{"line":10,"column":1},"end":{"line":10,"column":1}},"key":"P3gzEdIGIM"}],"key":"Rw0L5rD4Kz"},{"type":"tableCell","header":true,"position":{"start":{"line":10,"column":1},"end":{"line":10,"column":1}},"children":[{"type":"text","value":"Value","position":{"start":{"line":10,"column":1},"end":{"line":10,"column":1}},"key":"qc8SEwOe6D"}],"key":"Vtphx4LoHD"}],"key":"aOhMV0cQSX"},{"type":"tableRow","position":{"start":{"line":12,"column":1},"end":{"line":12,"column":1}},"children":[{"type":"tableCell","position":{"start":{"line":12,"column":1},"end":{"line":12,"column":1}},"children":[{"type":"strong","position":{"start":{"line":12,"column":1},"end":{"line":12,"column":1}},"children":[{"type":"text","value":"Size","position":{"start":{"line":12,"column":1},"end":{"line":12,"column":1}},"key":"J51QRF8x9c"}],"key":"qEET6zh6tv"}],"key":"NVMES1HRUG"},{"type":"tableCell","position":{"start":{"line":12,"column":1},"end":{"line":12,"column":1}},"children":[{"type":"text","value":"~1M structures (S2EF), ~10K structures (IS2RE)","position":{"start":{"line":12,"column":1},"end":{"line":12,"column":1}},"key":"vzoQfIzWyA"}],"key":"dwYD35z3IS"}],"key":"W5S5e2gPNf"},{"type":"tableRow","position":{"start":{"line":13,"column":1},"end":{"line":13,"column":1}},"children":[{"type":"tableCell","position":{"start":{"line":13,"column":1},"end":{"line":13,"column":1}},"children":[{"type":"strong","position":{"start":{"line":13,"column":1},"end":{"line":13,"column":1}},"children":[{"type":"text","value":"Domain","position":{"start":{"line":13,"column":1},"end":{"line":13,"column":1}},"key":"XYXThC8LCA"}],"key":"Jxa2q2H5Hg"}],"key":"cu6fWSwluY"},{"type":"tableCell","position":{"start":{"line":13,"column":1},"end":{"line":13,"column":1}},"children":[{"type":"text","value":"Metal-organic frameworks (MOFs) with CO2","position":{"start":{"line":13,"column":1},"end":{"line":13,"column":1}},"key":"eD8bgQUqOS"}],"key":"NS7Ifo18d5"}],"key":"M1G27H77fG"},{"type":"tableRow","position":{"start":{"line":14,"column":1},"end":{"line":14,"column":1}},"children":[{"type":"tableCell","position":{"start":{"line":14,"column":1},"end":{"line":14,"column":1}},"children":[{"type":"strong","position":{"start":{"line":14,"column":1},"end":{"line":14,"column":1}},"children":[{"type":"text","value":"Labels","position":{"start":{"line":14,"column":1},"end":{"line":14,"column":1}},"key":"HzkTlcOTcS"}],"key":"PgT8d0wf6P"}],"key":"QfzQHU7N2k"},{"type":"tableCell","position":{"start":{"line":14,"column":1},"end":{"line":14,"column":1}},"children":[{"type":"text","value":"Total energy (eV), forces (eV/A)","position":{"start":{"line":14,"column":1},"end":{"line":14,"column":1}},"key":"N06ClufXHl"}],"key":"TkOCrSr3Ni"}],"key":"G7FzgKRqtC"},{"type":"tableRow","position":{"start":{"line":15,"column":1},"end":{"line":15,"column":1}},"children":[{"type":"tableCell","position":{"start":{"line":15,"column":1},"end":{"line":15,"column":1}},"children":[{"type":"strong","position":{"start":{"line":15,"column":1},"end":{"line":15,"column":1}},"children":[{"type":"text","value":"Level of Theory","position":{"start":{"line":15,"column":1},"end":{"line":15,"column":1}},"key":"mC1SaYaoY7"}],"key":"Ys2MzZadH7"}],"key":"ycwj38sR1P"},{"type":"tableCell","position":{"start":{"line":15,"column":1},"end":{"line":15,"column":1}},"children":[{"type":"text","value":"PBE+D3 (VASP)","position":{"start":{"line":15,"column":1},"end":{"line":15,"column":1}},"key":"cDGgMFg11O"}],"key":"Ke8e2ndOa9"}],"key":"MDah7UBEB3"},{"type":"tableRow","position":{"start":{"line":16,"column":1},"end":{"line":16,"column":1}},"children":[{"type":"tableCell","position":{"start":{"line":16,"column":1},"end":{"line":16,"column":1}},"children":[{"type":"strong","position":{"start":{"line":16,"column":1},"end":{"line":16,"column":1}},"children":[{"type":"text","value":"License","position":{"start":{"line":16,"column":1},"end":{"line":16,"column":1}},"key":"b1HYVFtU2C"}],"key":"sLiBqEWQiL"}],"key":"FLoWClt18d"},{"type":"tableCell","position":{"start":{"line":16,"column":1},"end":{"line":16,"column":1}},"children":[{"type":"link","url":"https://creativecommons.org/licenses/by/4.0/legalcode","position":{"start":{"line":16,"column":1},"end":{"line":16,"column":1}},"children":[{"type":"text","value":"CC BY 4.0","position":{"start":{"line":16,"column":1},"end":{"line":16,"column":1}},"key":"erTkJ303Mq"}],"urlSource":"https://creativecommons.org/licenses/by/4.0/legalcode","key":"kqm2KUo26e"}],"key":"akpzWOm2bS"}],"key":"TlxyZjKreQ"},{"type":"tableRow","position":{"start":{"line":17,"column":1},"end":{"line":17,"column":1}},"children":[{"type":"tableCell","position":{"start":{"line":17,"column":1},"end":{"line":17,"column":1}},"children":[{"type":"strong","position":{"start":{"line":17,"column":1},"end":{"line":17,"column":1}},"children":[{"type":"text","value":"Status","position":{"start":{"line":17,"column":1},"end":{"line":17,"column":1}},"key":"RN1LeJOemK"}],"key":"jUcOnqSs2U"}],"key":"nQLGMXjAkT"},{"type":"tableCell","position":{"start":{"line":17,"column":1},"end":{"line":17,"column":1}},"children":[{"type":"text","value":"Deprecated - use ODAC25","position":{"start":{"line":17,"column":1},"end":{"line":17,"column":1}},"key":"YEGUFF8K8P"}],"key":"VC8qlJuHP7"}],"key":"FwRrlYQNHY"}],"key":"KVG6sbWnrK"}],"key":"DlHRpbf4di"},{"type":"heading","depth":2,"position":{"start":{"line":20,"column":1},"end":{"line":20,"column":1}},"children":[{"type":"text","value":"Structure to Energy and Forces (S2EF) task","position":{"start":{"line":20,"column":1},"end":{"line":20,"column":1}},"key":"E7JbE8tT0h"}],"identifier":"structure-to-energy-and-forces-s2ef-task","label":"Structure to Energy and Forces (S2EF) task","html_id":"structure-to-energy-and-forces-s2ef-task","implicit":true,"key":"Enan4bQQjD"},{"type":"paragraph","position":{"start":{"line":22,"column":1},"end":{"line":22,"column":1}},"children":[{"type":"text","value":"We provide precomputed LMDBs for train, validation, and the various test sets that can be used directly with the dataloaders provided in our code. The LMDBs contain input structures from all points in relaxation trajectories along with the energy of the structure and the atomic forces. The dataset contains an in-domain test set and 4 out-of-domain test sets (ood-large, ood-linker, ood-topology, and ood-linker & topology). All LMDbs  are compressed into a single ","position":{"start":{"line":22,"column":1},"end":{"line":22,"column":1}},"key":"vkBfhhb0Qa"},{"type":"inlineCode","value":".tar.gz","position":{"start":{"line":22,"column":1},"end":{"line":22,"column":1}},"key":"WqsRfEUzrf"},{"type":"text","value":" file.","position":{"start":{"line":22,"column":1},"end":{"line":22,"column":1}},"key":"h4W9ID0NMi"}],"key":"FIt9faAk0w"},{"type":"table","position":{"start":{"line":24,"column":1},"end":{"line":27,"column":1}},"children":[{"type":"tableRow","position":{"start":{"line":24,"column":1},"end":{"line":24,"column":1}},"children":[{"type":"tableCell","header":true,"position":{"start":{"line":24,"column":1},"end":{"line":24,"column":1}},"children":[{"type":"text","value":"Splits","position":{"start":{"line":24,"column":1},"end":{"line":24,"column":1}},"key":"Y4jStnEfHn"}],"key":"U5DlJg8Xfn"},{"type":"tableCell","header":true,"position":{"start":{"line":24,"column":1},"end":{"line":24,"column":1}},"children":[{"type":"text","value":"Size of compressed version (in bytes)","position":{"start":{"line":24,"column":1},"end":{"line":24,"column":1}},"key":"lRrSl2UIIN"}],"key":"J8oH17YCLj"},{"type":"tableCell","header":true,"position":{"start":{"line":24,"column":1},"end":{"line":24,"column":1}},"children":[{"type":"text","value":"Size of uncompressed version (in bytes)","position":{"start":{"line":24,"column":1},"end":{"line":24,"column":1}},"key":"Iht6CETcjf"}],"key":"vRWxq6LSvm"},{"type":"tableCell","header":true,"position":{"start":{"line":24,"column":1},"end":{"line":24,"column":1}},"children":[{"type":"text","value":"MD5 checksum (download link)","position":{"start":{"line":24,"column":1},"end":{"line":24,"column":1}},"key":"hSnBYkAX1f"}],"key":"hyx7w7wIpS"}],"key":"PK9Fi3t0Lt"},{"type":"tableRow","position":{"start":{"line":26,"column":1},"end":{"line":26,"column":1}},"children":[{"type":"tableCell","position":{"start":{"line":26,"column":1},"end":{"line":26,"column":1}},"children":[{"type":"text","value":"Train + Validation + Test (all splits)","position":{"start":{"line":26,"column":1},"end":{"line":26,"column":1}},"key":"fXJqKilT1S"}],"key":"HjyhmkBGMV"},{"type":"tableCell","position":{"start":{"line":26,"column":1},"end":{"line":26,"column":1}},"children":[{"type":"text","value":"172G","position":{"start":{"line":26,"column":1},"end":{"line":26,"column":1}},"key":"mzRk1Xfhql"}],"key":"bh8hHh8W7m"},{"type":"tableCell","position":{"start":{"line":26,"column":1},"end":{"line":26,"column":1}},"children":[{"type":"text","value":"476G","position":{"start":{"line":26,"column":1},"end":{"line":26,"column":1}},"key":"rQsgzY09gX"}],"key":"Q03tSVHQcM"},{"type":"tableCell","position":{"start":{"line":26,"column":1},"end":{"line":26,"column":1}},"children":[{"type":"link","url":"https://dl.fbaipublicfiles.com/large_objects/dac/datasets/odac23_s2ef.tar.gz","position":{"start":{"line":26,"column":1},"end":{"line":26,"column":1}},"children":[{"type":"text","value":"162f0660b2f1c9209c5b57f7b9e545a7","position":{"start":{"line":26,"column":1},"end":{"line":26,"column":1}},"key":"yE5pRxX4V0"}],"urlSource":"https://dl.fbaipublicfiles.com/large_objects/dac/datasets/odac23_s2ef.tar.gz","key":"SeWF8t3LdD"}],"key":"vcooD2lG1b"}],"key":"a5W9gjeiDN"},{"type":"tableRow","position":{"start":{"line":27,"column":1},"end":{"line":27,"column":1}},"children":[{"type":"tableCell","position":{"start":{"line":27,"column":1},"end":{"line":27,"column":1}},"children":[],"key":"XFhLtLiWeM"},{"type":"tableCell","position":{"start":{"line":27,"column":1},"end":{"line":27,"column":1}},"children":[],"key":"UsbC0C8Ygc"},{"type":"tableCell","position":{"start":{"line":27,"column":1},"end":{"line":27,"column":1}},"children":[],"key":"wFZbbx3Z8q"},{"type":"tableCell","position":{"start":{"line":27,"column":1},"end":{"line":27,"column":1}},"children":[],"key":"EhX0cEVWgK"}],"key":"eVXz9VpMDh"}],"key":"C9jPXe3Zoz"},{"type":"paragraph","position":{"start":{"line":29,"column":1},"end":{"line":29,"column":1}},"children":[{"type":"text","value":"The train and val splits are also available in ","position":{"start":{"line":29,"column":1},"end":{"line":29,"column":1}},"key":"R9feHiJnls"},{"type":"inlineCode","value":"extxyz","position":{"start":{"line":29,"column":1},"end":{"line":29,"column":1}},"key":"WSebSB4HRu"},{"type":"text","value":" formats. Each trajectory is in stored in a different ","position":{"start":{"line":29,"column":1},"end":{"line":29,"column":1}},"key":"xxeCIYjDO9"},{"type":"inlineCode","value":"extxyz","position":{"start":{"line":29,"column":1},"end":{"line":29,"column":1}},"key":"t3R9gPzTlj"},{"type":"text","value":" file.","position":{"start":{"line":29,"column":1},"end":{"line":29,"column":1}},"key":"uKnFvvlf3Y"}],"key":"fuv9gjHyrp"},{"type":"table","position":{"start":{"line":31,"column":1},"end":{"line":35,"column":1}},"children":[{"type":"tableRow","position":{"start":{"line":31,"column":1},"end":{"line":31,"column":1}},"children":[{"type":"tableCell","header":true,"position":{"start":{"line":31,"column":1},"end":{"line":31,"column":1}},"children":[{"type":"text","value":"Splits","position":{"start":{"line":31,"column":1},"end":{"line":31,"column":1}},"key":"rUUTqDZIIC"}],"key":"BtaZjQYAVL"},{"type":"tableCell","header":true,"position":{"start":{"line":31,"column":1},"end":{"line":31,"column":1}},"children":[{"type":"text","value":"Size of compressed version (in bytes)","position":{"start":{"line":31,"column":1},"end":{"line":31,"column":1}},"key":"GYbgftMy4q"}],"key":"Acf8T2IVM5"},{"type":"tableCell","header":true,"position":{"start":{"line":31,"column":1},"end":{"line":31,"column":1}},"children":[{"type":"text","value":"Size of uncompressed version (in bytes)","position":{"start":{"line":31,"column":1},"end":{"line":31,"column":1}},"key":"LRXKq8Apou"}],"key":"UxSICRbtIS"},{"type":"tableCell","header":true,"position":{"start":{"line":31,"column":1},"end":{"line":31,"column":1}},"children":[{"type":"text","value":"MD5 checksum (download link)","position":{"start":{"line":31,"column":1},"end":{"line":31,"column":1}},"key":"CYcZqzzqOJ"}],"key":"taKAwfkPTd"}],"key":"BwvvqdCtob"},{"type":"tableRow","position":{"start":{"line":33,"column":1},"end":{"line":33,"column":1}},"children":[{"type":"tableCell","position":{"start":{"line":33,"column":1},"end":{"line":33,"column":1}},"children":[{"type":"text","value":"Train","position":{"start":{"line":33,"column":1},"end":{"line":33,"column":1}},"key":"MajvJWQmSe"}],"key":"J6yfzoXG3M"},{"type":"tableCell","position":{"start":{"line":33,"column":1},"end":{"line":33,"column":1}},"children":[{"type":"text","value":"232G","position":{"start":{"line":33,"column":1},"end":{"line":33,"column":1}},"key":"VFt8LJxQSF"}],"key":"e1ftNFrP0D"},{"type":"tableCell","position":{"start":{"line":33,"column":1},"end":{"line":33,"column":1}},"children":[{"type":"text","value":"781G","position":{"start":{"line":33,"column":1},"end":{"line":33,"column":1}},"key":"tOSpRdQORm"}],"key":"XTN6e0Up9O"},{"type":"tableCell","position":{"start":{"line":33,"column":1},"end":{"line":33,"column":1}},"children":[{"type":"link","url":"https://dl.fbaipublicfiles.com/large_objects/dac/datasets/extxyz_train.tar.gz","position":{"start":{"line":33,"column":1},"end":{"line":33,"column":1}},"children":[{"type":"text","value":"381e72fd8b9c055065fd3afff6b0945b","position":{"start":{"line":33,"column":1},"end":{"line":33,"column":1}},"key":"rQVvd5OyYd"}],"urlSource":"https://dl.fbaipublicfiles.com/large_objects/dac/datasets/extxyz_train.tar.gz","key":"iwW74wgGvI"}],"key":"Su1dvybrN7"}],"key":"AWgtw1CzCY"},{"type":"tableRow","position":{"start":{"line":34,"column":1},"end":{"line":34,"column":1}},"children":[{"type":"tableCell","position":{"start":{"line":34,"column":1},"end":{"line":34,"column":1}},"children":[{"type":"text","value":"Val","position":{"start":{"line":34,"column":1},"end":{"line":34,"column":1}},"key":"wZkHI9Pyge"}],"key":"sHL9Bku4oT"},{"type":"tableCell","position":{"start":{"line":34,"column":1},"end":{"line":34,"column":1}},"children":[{"type":"text","value":"5.1G","position":{"start":{"line":34,"column":1},"end":{"line":34,"column":1}},"key":"idhE12c6X8"}],"key":"IL6cjvOT9I"},{"type":"tableCell","position":{"start":{"line":34,"column":1},"end":{"line":34,"column":1}},"children":[{"type":"text","value":"18G","position":{"start":{"line":34,"column":1},"end":{"line":34,"column":1}},"key":"wYXXJY7av3"}],"key":"EKsAu17kxU"},{"type":"tableCell","position":{"start":{"line":34,"column":1},"end":{"line":34,"column":1}},"children":[{"type":"link","url":"https://dl.fbaipublicfiles.com/dac/datasets/extxyz_val.tar.gz","position":{"start":{"line":34,"column":1},"end":{"line":34,"column":1}},"children":[{"type":"text","value":"09913759c6e0f8d649f7ec9dff9e0e8b","position":{"start":{"line":34,"column":1},"end":{"line":34,"column":1}},"key":"kDR1OpaWnG"}],"urlSource":"https://dl.fbaipublicfiles.com/dac/datasets/extxyz_val.tar.gz","key":"VYm24pWt9m"}],"key":"Qcyolqpn1q"}],"key":"Cqcf4Jy1ws"},{"type":"tableRow","position":{"start":{"line":35,"column":1},"end":{"line":35,"column":1}},"children":[{"type":"tableCell","position":{"start":{"line":35,"column":1},"end":{"line":35,"column":1}},"children":[],"key":"nlgY3LfGug"},{"type":"tableCell","position":{"start":{"line":35,"column":1},"end":{"line":35,"column":1}},"children":[],"key":"ggCn9mZExF"},{"type":"tableCell","position":{"start":{"line":35,"column":1},"end":{"line":35,"column":1}},"children":[],"key":"RyttEfsphJ"},{"type":"tableCell","position":{"start":{"line":35,"column":1},"end":{"line":35,"column":1}},"children":[],"key":"wBChWaucVq"}],"key":"JhcSXjNRgx"}],"key":"AnyxFCEbVE"},{"type":"heading","depth":2,"position":{"start":{"line":37,"column":1},"end":{"line":37,"column":1}},"children":[{"type":"text","value":"Initial Structure to Relaxed Structure (IS2RS) / Relaxed Energy (IS2RE) tasks","position":{"start":{"line":37,"column":1},"end":{"line":37,"column":1}},"key":"NpEiHCcfr3"}],"identifier":"initial-structure-to-relaxed-structure-is2rs-relaxed-energy-is2re-tasks","label":"Initial Structure to Relaxed Structure (IS2RS) / Relaxed Energy (IS2RE) tasks","html_id":"initial-structure-to-relaxed-structure-is2rs-relaxed-energy-is2re-tasks","implicit":true,"key":"B6ss0EsqbO"},{"type":"paragraph","position":{"start":{"line":39,"column":1},"end":{"line":39,"column":1}},"children":[{"type":"text","value":"For IS2RE / IS2RS training, validation and test sets, we provide precomputed LMDBs that can be directly used with dataloaders provided in our code. The LMDBs contain input initial structures and the output relaxed structures and energies. The dataset contains an in-domain test set and 4 out-of-domain test sets (ood-large, ood-linker, ood-topology, and ood-linker & topology). All LMDBs are compressed into a single ","position":{"start":{"line":39,"column":1},"end":{"line":39,"column":1}},"key":"K5y75kLT21"},{"type":"inlineCode","value":".tar.gz","position":{"start":{"line":39,"column":1},"end":{"line":39,"column":1}},"key":"YyIcayw57A"},{"type":"text","value":" file.","position":{"start":{"line":39,"column":1},"end":{"line":39,"column":1}},"key":"mwOYSSYHec"}],"key":"LCYgeHwNph"},{"type":"table","position":{"start":{"line":42,"column":1},"end":{"line":45,"column":1}},"children":[{"type":"tableRow","position":{"start":{"line":42,"column":1},"end":{"line":42,"column":1}},"children":[{"type":"tableCell","header":true,"position":{"start":{"line":42,"column":1},"end":{"line":42,"column":1}},"children":[{"type":"text","value":"Splits","position":{"start":{"line":42,"column":1},"end":{"line":42,"column":1}},"key":"el4yUisx9o"}],"key":"IITk4N6LZI"},{"type":"tableCell","header":true,"position":{"start":{"line":42,"column":1},"end":{"line":42,"column":1}},"children":[{"type":"text","value":"Size of compressed version (in bytes)","position":{"start":{"line":42,"column":1},"end":{"line":42,"column":1}},"key":"i1cy7NBVpu"}],"key":"sLT2hi0b1d"},{"type":"tableCell","header":true,"position":{"start":{"line":42,"column":1},"end":{"line":42,"column":1}},"children":[{"type":"text","value":"Size of uncompressed version (in bytes)","position":{"start":{"line":42,"column":1},"end":{"line":42,"column":1}},"key":"kfxY2zdDPr"}],"key":"qfNnz0qlv4"},{"type":"tableCell","header":true,"position":{"start":{"line":42,"column":1},"end":{"line":42,"column":1}},"children":[{"type":"text","value":"MD5 checksum (download link)","position":{"start":{"line":42,"column":1},"end":{"line":42,"column":1}},"key":"BScypPq68b"}],"key":"zYTmfHy4B7"}],"key":"GmCw6e2BPo"},{"type":"tableRow","position":{"start":{"line":44,"column":1},"end":{"line":44,"column":1}},"children":[{"type":"tableCell","position":{"start":{"line":44,"column":1},"end":{"line":44,"column":1}},"children":[{"type":"text","value":"Train + Validation + Test (all splits)","position":{"start":{"line":44,"column":1},"end":{"line":44,"column":1}},"key":"zpMrqVaRvh"}],"key":"t2G9664r5h"},{"type":"tableCell","position":{"start":{"line":44,"column":1},"end":{"line":44,"column":1}},"children":[{"type":"text","value":"809M","position":{"start":{"line":44,"column":1},"end":{"line":44,"column":1}},"key":"kvTSNSuScg"}],"key":"U9HAyiXXQ1"},{"type":"tableCell","position":{"start":{"line":44,"column":1},"end":{"line":44,"column":1}},"children":[{"type":"text","value":"2.2G","position":{"start":{"line":44,"column":1},"end":{"line":44,"column":1}},"key":"Pox77jCyoK"}],"key":"CEHzX0pnHV"},{"type":"tableCell","position":{"start":{"line":44,"column":1},"end":{"line":44,"column":1}},"children":[{"type":"link","url":"https://dl.fbaipublicfiles.com/dac/datasets/odac23_is2r.tar.gz","position":{"start":{"line":44,"column":1},"end":{"line":44,"column":1}},"children":[{"type":"text","value":"f7f2f58669a30abae8cb9ba1b7f2bcd2","position":{"start":{"line":44,"column":1},"end":{"line":44,"column":1}},"key":"bzVTqY0vwG"}],"urlSource":"https://dl.fbaipublicfiles.com/dac/datasets/odac23_is2r.tar.gz","key":"RqFOqWqnbO"}],"key":"BToBOdqdve"}],"key":"gTqaoMwALa"},{"type":"tableRow","position":{"start":{"line":45,"column":1},"end":{"line":45,"column":1}},"children":[{"type":"tableCell","position":{"start":{"line":45,"column":1},"end":{"line":45,"column":1}},"children":[],"key":"hTJqncroed"},{"type":"tableCell","position":{"start":{"line":45,"column":1},"end":{"line":45,"column":1}},"children":[],"key":"UFRRx2opRi"},{"type":"tableCell","position":{"start":{"line":45,"column":1},"end":{"line":45,"column":1}},"children":[],"key":"GymUw1Cf84"},{"type":"tableCell","position":{"start":{"line":45,"column":1},"end":{"line":45,"column":1}},"children":[],"key":"rjv3JbG5Qw"}],"key":"yyUFtbwxGz"}],"key":"E1rhPyVGLz"},{"type":"heading","depth":2,"position":{"start":{"line":47,"column":1},"end":{"line":47,"column":1}},"children":[{"type":"text","value":"DDEC Charges","position":{"start":{"line":47,"column":1},"end":{"line":47,"column":1}},"key":"I602Z2j8uD"}],"identifier":"ddec-charges","label":"DDEC Charges","html_id":"ddec-charges","implicit":true,"key":"SoGQuMsgJI"},{"type":"paragraph","position":{"start":{"line":49,"column":1},"end":{"line":49,"column":1}},"children":[{"type":"text","value":"We provide DDEC charges computed for all MOFs in the ODAC23 dataset. A small number of MOFs (~2%) are missing these charges because the DDEC calcuations failed for them.","position":{"start":{"line":49,"column":1},"end":{"line":49,"column":1}},"key":"Bz05ZbAGPD"}],"key":"f4aGQcyJTt"},{"type":"table","position":{"start":{"line":51,"column":1},"end":{"line":54,"column":1}},"children":[{"type":"tableRow","position":{"start":{"line":51,"column":1},"end":{"line":51,"column":1}},"children":[{"type":"tableCell","header":true,"position":{"start":{"line":51,"column":1},"end":{"line":51,"column":1}},"children":[{"type":"text","value":"Size of compressed version (in bytes)","position":{"start":{"line":51,"column":1},"end":{"line":51,"column":1}},"key":"ajgtQekm1Q"}],"key":"k3Y7MlNcV1"},{"type":"tableCell","header":true,"position":{"start":{"line":51,"column":1},"end":{"line":51,"column":1}},"children":[{"type":"text","value":"Size of uncompressed version (in bytes)","position":{"start":{"line":51,"column":1},"end":{"line":51,"column":1}},"key":"Jymcmpytu7"}],"key":"BrbyFMOYNN"},{"type":"tableCell","header":true,"position":{"start":{"line":51,"column":1},"end":{"line":51,"column":1}},"children":[{"type":"text","value":"MD5 checksum (download link)","position":{"start":{"line":51,"column":1},"end":{"line":51,"column":1}},"key":"P2qLkxr6VF"}],"key":"LyGBTsO4NS"}],"key":"Z1JRgs60NS"},{"type":"tableRow","position":{"start":{"line":53,"column":1},"end":{"line":53,"column":1}},"children":[{"type":"tableCell","position":{"start":{"line":53,"column":1},"end":{"line":53,"column":1}},"children":[{"type":"text","value":"147M","position":{"start":{"line":53,"column":1},"end":{"line":53,"column":1}},"key":"NZocOgWygE"}],"key":"nZzFyDPsjF"},{"type":"tableCell","position":{"start":{"line":53,"column":1},"end":{"line":53,"column":1}},"children":[{"type":"text","value":"534M","position":{"start":{"line":53,"column":1},"end":{"line":53,"column":1}},"key":"soWfq3sP4E"}],"key":"ayEwr5lvjH"},{"type":"tableCell","position":{"start":{"line":53,"column":1},"end":{"line":53,"column":1}},"children":[{"type":"link","url":"https://dl.fbaipublicfiles.com/dac/datasets/ddec.tar.gz","position":{"start":{"line":53,"column":1},"end":{"line":53,"column":1}},"children":[{"type":"text","value":"81927b78d9e4184cc3c398e79760126a","position":{"start":{"line":53,"column":1},"end":{"line":53,"column":1}},"key":"mWKrdxGlt8"}],"urlSource":"https://dl.fbaipublicfiles.com/dac/datasets/ddec.tar.gz","key":"DaS2Z5VTyt"}],"key":"PyOf2nzAr6"}],"key":"s1kdzmRBBi"},{"type":"tableRow","position":{"start":{"line":54,"column":1},"end":{"line":54,"column":1}},"children":[{"type":"tableCell","position":{"start":{"line":54,"column":1},"end":{"line":54,"column":1}},"children":[],"key":"LiEmBn095H"},{"type":"tableCell","position":{"start":{"line":54,"column":1},"end":{"line":54,"column":1}},"children":[],"key":"PI2vEFrTI1"},{"type":"tableCell","position":{"start":{"line":54,"column":1},"end":{"line":54,"column":1}},"children":[],"key":"MwJqR5Iu8R"}],"key":"wku9qno6RO"}],"key":"RLP2ENnqGK"},{"type":"heading","depth":2,"position":{"start":{"line":57,"column":1},"end":{"line":57,"column":1}},"children":[{"type":"text","value":"Citing ODAC23","position":{"start":{"line":57,"column":1},"end":{"line":57,"column":1}},"key":"dIuGZbQndW"}],"identifier":"citing-odac23","label":"Citing ODAC23","html_id":"citing-odac23","implicit":true,"key":"FcBaV8NvTX"},{"type":"paragraph","position":{"start":{"line":59,"column":1},"end":{"line":59,"column":1}},"children":[{"type":"text","value":"The OpenDAC 2023 (ODAC23) dataset is licensed under a ","position":{"start":{"line":59,"column":1},"end":{"line":59,"column":1}},"key":"fkYSPkDDMT"},{"type":"link","url":"https://creativecommons.org/licenses/by/4.0/legalcode","position":{"start":{"line":59,"column":1},"end":{"line":59,"column":1}},"children":[{"type":"text","value":"Creative Commons Attribution 4.0 License","position":{"start":{"line":59,"column":1},"end":{"line":59,"column":1}},"key":"eWdFp5oSU9"}],"urlSource":"https://creativecommons.org/licenses/by/4.0/legalcode","key":"B6lCVzKmCG"},{"type":"text","value":".","position":{"start":{"line":59,"column":1},"end":{"line":59,"column":1}},"key":"EmsmJktBRa"}],"key":"xKSXzMl9r5"},{"type":"paragraph","position":{"start":{"line":61,"column":1},"end":{"line":61,"column":1}},"children":[{"type":"text","value":"Please consider citing the following paper in any research manuscript using the ODAC23 dataset:","position":{"start":{"line":61,"column":1},"end":{"line":61,"column":1}},"key":"VEOUiGtezL"}],"key":"QXiqh5vkbd"},{"type":"code","lang":"bibtex","value":"@article{odac23_dataset,\n    author = {Anuroop Sriram and Sihoon Choi and Xiaohan Yu and Logan M. Brabson and Abhishek Das and Zachary Ulissi and Matt Uyttendaele and Andrew J. Medford and David S. Sholl},\n    title = {The Open DAC 2023 Dataset and Challenges for Sorbent Discovery in Direct Air Capture},\n    year = {2023},\n    journal={arXiv preprint arXiv:2311.00341},\n}","position":{"start":{"line":64,"column":1},"end":{"line":71,"column":1}},"key":"STrDOy5bph"}],"key":"e974HgEUY2"}],"key":"HNAdIc9cBL"},"references":{"cite":{"order":[],"data":{}}},"footer":{"navigation":{"prev":{"title":"ODAC25","url":"/odac25","group":"MOFs for Direct Air Capture"},"next":{"title":"Pretrained models","url":"/models-3","group":"MOFs for Direct Air Capture"}}},"domain":"http://localhost:3000"}