{"version":3,"kind":"Article","sha256":"719aab3bf77d018d13bbbe539fce2656456f840e733dbeec3932c34a56206463","slug":"odac25","location":"/dac/datasets/odac25.md","dependencies":[],"frontmatter":{"title":"ODAC25","content_includes_title":false,"authors":[{"nameParsed":{"literal":"FAIR Chemistry & Collaborators","given":"FAIR Chemistry &","family":"Collaborators"},"name":"FAIR Chemistry & Collaborators","id":"contributors-myst-generated-uid-0"}],"github":"https://github.com/facebookresearch/fairchem","copyright":"Meta Platforms, Inc","numbering":{"title":{"offset":2}},"source_url":"https://github.com/facebookresearch/fairchem/blob/main/docs/dac/datasets/odac25.md","edit_url":"https://github.com/facebookresearch/fairchem/edit/main/docs/dac/datasets/odac25.md","exports":[{"format":"md","filename":"odac25.md","url":"/build/odac25-c5a43a879b9aff26986a2d5ff6f8c371.md"}]},"mdast":{"type":"root","children":[{"type":"block","children":[{"type":"card","children":[{"type":"cardTitle","children":[{"type":"text","value":"Dataset Overview","position":{"start":{"line":3,"column":1},"end":{"line":3,"column":1}},"key":"rAs8c1FvWL"}],"key":"rJSlXqf6Bl"},{"type":"table","position":{"start":{"line":5,"column":1},"end":{"line":14,"column":1}},"children":[{"type":"tableRow","position":{"start":{"line":5,"column":1},"end":{"line":5,"column":1}},"children":[{"type":"tableCell","header":true,"position":{"start":{"line":5,"column":1},"end":{"line":5,"column":1}},"children":[{"type":"text","value":"Property","position":{"start":{"line":5,"column":1},"end":{"line":5,"column":1}},"key":"TLFM629BhC"}],"key":"q58V1bf4l7"},{"type":"tableCell","header":true,"position":{"start":{"line":5,"column":1},"end":{"line":5,"column":1}},"children":[{"type":"text","value":"Value","position":{"start":{"line":5,"column":1},"end":{"line":5,"column":1}},"key":"TDRinURyzP"}],"key":"rytgoNPH4B"}],"key":"eLXNOaw48C"},{"type":"tableRow","position":{"start":{"line":7,"column":1},"end":{"line":7,"column":1}},"children":[{"type":"tableCell","position":{"start":{"line":7,"column":1},"end":{"line":7,"column":1}},"children":[{"type":"strong","position":{"start":{"line":7,"column":1},"end":{"line":7,"column":1}},"children":[{"type":"text","value":"Size","position":{"start":{"line":7,"column":1},"end":{"line":7,"column":1}},"key":"i62chEbCe6"}],"key":"nrXT0O4JWU"}],"key":"Br0FzcwJ7d"},{"type":"tableCell","position":{"start":{"line":7,"column":1},"end":{"line":7,"column":1}},"children":[{"type":"text","value":"~70 million DFT calculations","position":{"start":{"line":7,"column":1},"end":{"line":7,"column":1}},"key":"OeQVtDlhta"}],"key":"parlPrRIC6"}],"key":"nAK1Dhh0C6"},{"type":"tableRow","position":{"start":{"line":8,"column":1},"end":{"line":8,"column":1}},"children":[{"type":"tableCell","position":{"start":{"line":8,"column":1},"end":{"line":8,"column":1}},"children":[{"type":"strong","position":{"start":{"line":8,"column":1},"end":{"line":8,"column":1}},"children":[{"type":"text","value":"Domain","position":{"start":{"line":8,"column":1},"end":{"line":8,"column":1}},"key":"r2HHEYGGt6"}],"key":"zmGTUH5oqv"}],"key":"Ybpn7zIDue"},{"type":"tableCell","position":{"start":{"line":8,"column":1},"end":{"line":8,"column":1}},"children":[{"type":"text","value":"Metal-organic frameworks (MOFs)","position":{"start":{"line":8,"column":1},"end":{"line":8,"column":1}},"key":"juIwN6itVm"}],"key":"SzbS07tO3A"}],"key":"GAIUJSK0uL"},{"type":"tableRow","position":{"start":{"line":9,"column":1},"end":{"line":9,"column":1}},"children":[{"type":"tableCell","position":{"start":{"line":9,"column":1},"end":{"line":9,"column":1}},"children":[{"type":"strong","position":{"start":{"line":9,"column":1},"end":{"line":9,"column":1}},"children":[{"type":"text","value":"Adsorbates","position":{"start":{"line":9,"column":1},"end":{"line":9,"column":1}},"key":"IdGyVwOnTn"}],"key":"ZaYnYAfKrJ"}],"key":"Rcb02TEhvZ"},{"type":"tableCell","position":{"start":{"line":9,"column":1},"end":{"line":9,"column":1}},"children":[{"type":"text","value":"CO2, H2O, N2, O2","position":{"start":{"line":9,"column":1},"end":{"line":9,"column":1}},"key":"SU7WV8W374"}],"key":"vd77ZhxF3Q"}],"key":"HeLgGU5sIP"},{"type":"tableRow","position":{"start":{"line":10,"column":1},"end":{"line":10,"column":1}},"children":[{"type":"tableCell","position":{"start":{"line":10,"column":1},"end":{"line":10,"column":1}},"children":[{"type":"strong","position":{"start":{"line":10,"column":1},"end":{"line":10,"column":1}},"children":[{"type":"text","value":"MOFs","position":{"start":{"line":10,"column":1},"end":{"line":10,"column":1}},"key":"oLWpV1awDA"}],"key":"qXdn5z7awz"}],"key":"KTraJ05fPP"},{"type":"tableCell","position":{"start":{"line":10,"column":1},"end":{"line":10,"column":1}},"children":[{"type":"text","value":"~15,000 structures","position":{"start":{"line":10,"column":1},"end":{"line":10,"column":1}},"key":"jWmzRmlgo3"}],"key":"IFBlTh5l99"}],"key":"DPrRkolC74"},{"type":"tableRow","position":{"start":{"line":11,"column":1},"end":{"line":11,"column":1}},"children":[{"type":"tableCell","position":{"start":{"line":11,"column":1},"end":{"line":11,"column":1}},"children":[{"type":"strong","position":{"start":{"line":11,"column":1},"end":{"line":11,"column":1}},"children":[{"type":"text","value":"Labels","position":{"start":{"line":11,"column":1},"end":{"line":11,"column":1}},"key":"qcCrJm5CcW"}],"key":"V88H2j1k5q"}],"key":"qMSHAGQHhZ"},{"type":"tableCell","position":{"start":{"line":11,"column":1},"end":{"line":11,"column":1}},"children":[{"type":"text","value":"Total energy (eV), forces (eV/A)","position":{"start":{"line":11,"column":1},"end":{"line":11,"column":1}},"key":"FY00yQrW6n"}],"key":"rL8jF5lnGJ"}],"key":"RDyLA4JcQq"},{"type":"tableRow","position":{"start":{"line":12,"column":1},"end":{"line":12,"column":1}},"children":[{"type":"tableCell","position":{"start":{"line":12,"column":1},"end":{"line":12,"column":1}},"children":[{"type":"strong","position":{"start":{"line":12,"column":1},"end":{"line":12,"column":1}},"children":[{"type":"text","value":"Level of Theory","position":{"start":{"line":12,"column":1},"end":{"line":12,"column":1}},"key":"VxmQR8slzt"}],"key":"YDZOMWivzZ"}],"key":"ZQWdt7QvEr"},{"type":"tableCell","position":{"start":{"line":12,"column":1},"end":{"line":12,"column":1}},"children":[{"type":"text","value":"PBE+D3 (VASP)","position":{"start":{"line":12,"column":1},"end":{"line":12,"column":1}},"key":"pPoWWoyqQn"}],"key":"vPtx6kCugH"}],"key":"paCF50oeZc"},{"type":"tableRow","position":{"start":{"line":13,"column":1},"end":{"line":13,"column":1}},"children":[{"type":"tableCell","position":{"start":{"line":13,"column":1},"end":{"line":13,"column":1}},"children":[{"type":"strong","position":{"start":{"line":13,"column":1},"end":{"line":13,"column":1}},"children":[{"type":"text","value":"License","position":{"start":{"line":13,"column":1},"end":{"line":13,"column":1}},"key":"CBuUl0M2yL"}],"key":"tqTyLIDVkY"}],"key":"ZRF7zpZFjT"},{"type":"tableCell","position":{"start":{"line":13,"column":1},"end":{"line":13,"column":1}},"children":[{"type":"link","url":"https://creativecommons.org/licenses/by/4.0/legalcode","position":{"start":{"line":13,"column":1},"end":{"line":13,"column":1}},"children":[{"type":"text","value":"CC BY 4.0","position":{"start":{"line":13,"column":1},"end":{"line":13,"column":1}},"key":"v0cxjUVcZu"}],"urlSource":"https://creativecommons.org/licenses/by/4.0/legalcode","key":"DTNjHMQykf"}],"key":"IHUwjft7Kr"}],"key":"m2repmODUC"},{"type":"tableRow","position":{"start":{"line":14,"column":1},"end":{"line":14,"column":1}},"children":[{"type":"tableCell","position":{"start":{"line":14,"column":1},"end":{"line":14,"column":1}},"children":[{"type":"strong","position":{"start":{"line":14,"column":1},"end":{"line":14,"column":1}},"children":[{"type":"text","value":"Download","position":{"start":{"line":14,"column":1},"end":{"line":14,"column":1}},"key":"aw0y5a3Feu"}],"key":"uYSXSK5XYQ"}],"key":"PAW70F1WI8"},{"type":"tableCell","position":{"start":{"line":14,"column":1},"end":{"line":14,"column":1}},"children":[{"type":"link","url":"https://huggingface.co/facebook/ODAC25","position":{"start":{"line":14,"column":1},"end":{"line":14,"column":1}},"children":[{"type":"text","value":"HuggingFace","position":{"start":{"line":14,"column":1},"end":{"line":14,"column":1}},"key":"DTkyYxaCXX"}],"urlSource":"https://huggingface.co/facebook/ODAC25","key":"s40Z7DGlhh"}],"key":"Qcz0Pv0KxS"}],"key":"kGPpzrAluu"}],"key":"ZHeZgflyfV"}],"key":"BqCCMzciKI"},{"type":"paragraph","position":{"start":{"line":17,"column":1},"end":{"line":21,"column":1}},"children":[{"type":"text","value":"The Open DAC 2025 (ODAC25) dataset contains nearly 70 million DFT single-point\ncalculations for CO2, H2O, N2, and O2 adsorption in nearly 15,000 metal-organic frameworks\n(MOFs). This dataset represents a significant expansion upon ODAC23, introducing\ngreater chemical and configurational diversity through functionalized MOFs,\nhigh-energy GCMC-derived placements, and synthetically generated frameworks.","position":{"start":{"line":17,"column":1},"end":{"line":17,"column":1}},"key":"eRotpy2HyU"}],"key":"aMLmPcCS2V"},{"type":"paragraph","position":{"start":{"line":23,"column":1},"end":{"line":26,"column":1}},"children":[{"type":"text","value":"The dataset enables training of state-of-the-art machine-learned interatomic\npotentials for direct air capture applications. All structures are labeled\nwith total energies (eV) and forces (eV/Å) computed using VASP with the\nPBE+D3 functional.","position":{"start":{"line":23,"column":1},"end":{"line":23,"column":1}},"key":"Tg9HOQFjcn"}],"key":"KtmBCkXaf1"},{"type":"paragraph","position":{"start":{"line":28,"column":1},"end":{"line":30,"column":1}},"children":[{"type":"text","value":"All information about the dataset is available at the\n","position":{"start":{"line":28,"column":1},"end":{"line":28,"column":1}},"key":"Xuonjpno9f"},{"type":"link","url":"https://huggingface.co/facebook/ODAC25","position":{"start":{"line":28,"column":1},"end":{"line":28,"column":1}},"children":[{"type":"text","value":"ODAC25 Huggingface site","position":{"start":{"line":28,"column":1},"end":{"line":28,"column":1}},"key":"E9giBvhvvL"}],"urlSource":"https://huggingface.co/facebook/ODAC25","key":"QawhO7pNXt"},{"type":"text","value":".\nFor questions or issues, please open a GitHub issue in this repository.","position":{"start":{"line":28,"column":1},"end":{"line":28,"column":1}},"key":"qoiqcZMMuz"}],"key":"zHvsmiThmu"},{"type":"heading","depth":2,"position":{"start":{"line":32,"column":1},"end":{"line":32,"column":1}},"children":[{"type":"text","value":"Dataset format","position":{"start":{"line":32,"column":1},"end":{"line":32,"column":1}},"key":"BgbfkgrLUv"}],"identifier":"dataset-format","label":"Dataset format","html_id":"dataset-format","implicit":true,"key":"v79aLIqtrn"},{"type":"paragraph","position":{"start":{"line":34,"column":1},"end":{"line":34,"column":1}},"children":[{"type":"text","value":"The dataset is provided in ASE DB compatible lmdb files (","position":{"start":{"line":34,"column":1},"end":{"line":34,"column":1}},"key":"vhQ3ziSDfe"},{"type":"inlineCode","value":"*.aselmdb","position":{"start":{"line":34,"column":1},"end":{"line":34,"column":1}},"key":"VIwZvAHAzj"},{"type":"text","value":").","position":{"start":{"line":34,"column":1},"end":{"line":34,"column":1}},"key":"Eog8JQnlXh"}],"key":"JKa4XGyokR"},{"type":"heading","depth":3,"position":{"start":{"line":36,"column":1},"end":{"line":36,"column":1}},"children":[{"type":"text","value":"Citing ODAC25","position":{"start":{"line":36,"column":1},"end":{"line":36,"column":1}},"key":"dDxKFFb970"}],"identifier":"citing-odac25","label":"Citing ODAC25","html_id":"citing-odac25","implicit":true,"key":"RFmpTJOyJZ"},{"type":"paragraph","position":{"start":{"line":38,"column":1},"end":{"line":38,"column":1}},"children":[{"type":"text","value":"The ODAC25 dataset is licensed under a ","position":{"start":{"line":38,"column":1},"end":{"line":38,"column":1}},"key":"gkEOn0xxJx"},{"type":"link","url":"https://creativecommons.org/licenses/by/4.0/legalcode","position":{"start":{"line":38,"column":1},"end":{"line":38,"column":1}},"children":[{"type":"text","value":"Creative Commons Attribution 4.0 License","position":{"start":{"line":38,"column":1},"end":{"line":38,"column":1}},"key":"ZM5lRVf6uU"}],"urlSource":"https://creativecommons.org/licenses/by/4.0/legalcode","key":"ml2EkAjQZ2"},{"type":"text","value":".","position":{"start":{"line":38,"column":1},"end":{"line":38,"column":1}},"key":"vztDlLd45c"}],"key":"nC2XgxoBtZ"},{"type":"paragraph","position":{"start":{"line":40,"column":1},"end":{"line":40,"column":1}},"children":[{"type":"text","value":"Please consider citing the following paper in any publications that uses this dataset:","position":{"start":{"line":40,"column":1},"end":{"line":40,"column":1}},"key":"rm8hm58Sbs"}],"key":"muWn9vfymf"},{"type":"code","lang":"bib","value":"@misc{sriram2025odac25,\n    title={The Open DAC 2025 Dataset for Sorbent Discovery in Direct Air Capture}, \n    author={Anuroop Sriram and Logan M. Brabson and Xiaohan Yu and Sihoon Choi and Kareem Abdelmaqsoud and Elias Moubarak and Pim de Haan and Sindy Löwe and Johann Brehmer and John R. Kitchin and Max Welling and C. Lawrence Zitnick and Zachary Ulissi and Andrew J. Medford and David S. Sholl},\n    year={2025},\n    eprint={},\n    archivePrefix={arXiv},\n    primaryClass={},\n    url={}, \n}","position":{"start":{"line":42,"column":1},"end":{"line":52,"column":1}},"key":"GlzHv1XGed"}],"key":"epB9GWObEJ"}],"key":"dtwaxFfgVw"},"references":{"cite":{"order":[],"data":{}}},"footer":{"navigation":{"prev":{"title":"Datasets","url":"/summary-7","group":"MOFs for Direct Air Capture"},"next":{"title":"Open Direct Air Capture 2023 (ODAC23)","url":"/odac23","group":"MOFs for Direct Air Capture"}}},"domain":"http://localhost:3000"}