{"version":3,"kind":"Article","sha256":"8d487ddde16e5b43c9655199e4af889940accf3f58610392138468306d63d7df","slug":"omat24","location":"/inorganic_materials/datasets/omat24.md","dependencies":[],"frontmatter":{"title":"OMat24","content_includes_title":false,"authors":[{"nameParsed":{"literal":"FAIR Chemistry & Collaborators","given":"FAIR Chemistry &","family":"Collaborators"},"name":"FAIR Chemistry & Collaborators","id":"contributors-myst-generated-uid-0"}],"github":"https://github.com/facebookresearch/fairchem","copyright":"Meta Platforms, Inc","numbering":{"title":{"offset":2}},"source_url":"https://github.com/facebookresearch/fairchem/blob/main/docs/inorganic_materials/datasets/omat24.md","edit_url":"https://github.com/facebookresearch/fairchem/edit/main/docs/inorganic_materials/datasets/omat24.md","exports":[{"format":"md","filename":"omat24.md","url":"/build/omat24-2a26078c1f94523d94c6170ab3222b3c.md"}]},"mdast":{"type":"root","children":[{"type":"block","children":[{"type":"card","children":[{"type":"cardTitle","children":[{"type":"text","value":"Dataset Overview","position":{"start":{"line":3,"column":1},"end":{"line":3,"column":1}},"key":"WfQT7gDwr1"}],"key":"FwQBRn5hCt"},{"type":"table","position":{"start":{"line":5,"column":1},"end":{"line":12,"column":1}},"children":[{"type":"tableRow","position":{"start":{"line":5,"column":1},"end":{"line":5,"column":1}},"children":[{"type":"tableCell","header":true,"position":{"start":{"line":5,"column":1},"end":{"line":5,"column":1}},"children":[{"type":"text","value":"Property","position":{"start":{"line":5,"column":1},"end":{"line":5,"column":1}},"key":"P6gxZIHwHO"}],"key":"p3Un425tQO"},{"type":"tableCell","header":true,"position":{"start":{"line":5,"column":1},"end":{"line":5,"column":1}},"children":[{"type":"text","value":"Value","position":{"start":{"line":5,"column":1},"end":{"line":5,"column":1}},"key":"KTmlEqu5Ri"}],"key":"fbVMIzMTPh"}],"key":"t4r3XVMDzd"},{"type":"tableRow","position":{"start":{"line":7,"column":1},"end":{"line":7,"column":1}},"children":[{"type":"tableCell","position":{"start":{"line":7,"column":1},"end":{"line":7,"column":1}},"children":[{"type":"strong","position":{"start":{"line":7,"column":1},"end":{"line":7,"column":1}},"children":[{"type":"text","value":"Size","position":{"start":{"line":7,"column":1},"end":{"line":7,"column":1}},"key":"FL1kZ2XH3A"}],"key":"ow2ep4YPZI"}],"key":"BJ1m8krC61"},{"type":"tableCell","position":{"start":{"line":7,"column":1},"end":{"line":7,"column":1}},"children":[{"type":"text","value":"1.07M structures (train) + 1.02M (val)","position":{"start":{"line":7,"column":1},"end":{"line":7,"column":1}},"key":"e0pOXlGpr9"}],"key":"YUa3QdQfIo"}],"key":"wpqDwG5sHU"},{"type":"tableRow","position":{"start":{"line":8,"column":1},"end":{"line":8,"column":1}},"children":[{"type":"tableCell","position":{"start":{"line":8,"column":1},"end":{"line":8,"column":1}},"children":[{"type":"strong","position":{"start":{"line":8,"column":1},"end":{"line":8,"column":1}},"children":[{"type":"text","value":"Domain","position":{"start":{"line":8,"column":1},"end":{"line":8,"column":1}},"key":"cWEsD03oeo"}],"key":"IKyB7Jor4U"}],"key":"lF0VItEbjL"},{"type":"tableCell","position":{"start":{"line":8,"column":1},"end":{"line":8,"column":1}},"children":[{"type":"text","value":"Inorganic bulk materials","position":{"start":{"line":8,"column":1},"end":{"line":8,"column":1}},"key":"HEJgbTuMlD"}],"key":"HYWFxL5dwg"}],"key":"wJfsOTnPzh"},{"type":"tableRow","position":{"start":{"line":9,"column":1},"end":{"line":9,"column":1}},"children":[{"type":"tableCell","position":{"start":{"line":9,"column":1},"end":{"line":9,"column":1}},"children":[{"type":"strong","position":{"start":{"line":9,"column":1},"end":{"line":9,"column":1}},"children":[{"type":"text","value":"Labels","position":{"start":{"line":9,"column":1},"end":{"line":9,"column":1}},"key":"oO1ZeV33G1"}],"key":"XncCzaur1l"}],"key":"lwZTBpb8iH"},{"type":"tableCell","position":{"start":{"line":9,"column":1},"end":{"line":9,"column":1}},"children":[{"type":"text","value":"Total energy (eV), forces (eV/A), stress (eV/A^3)","position":{"start":{"line":9,"column":1},"end":{"line":9,"column":1}},"key":"q6gfm07Yir"}],"key":"Lkfhim45AR"}],"key":"qVmZLEb5nY"},{"type":"tableRow","position":{"start":{"line":10,"column":1},"end":{"line":10,"column":1}},"children":[{"type":"tableCell","position":{"start":{"line":10,"column":1},"end":{"line":10,"column":1}},"children":[{"type":"strong","position":{"start":{"line":10,"column":1},"end":{"line":10,"column":1}},"children":[{"type":"text","value":"Level of Theory","position":{"start":{"line":10,"column":1},"end":{"line":10,"column":1}},"key":"tJeCrhNLWD"}],"key":"SbiP0GO1fU"}],"key":"qxSuiLBVKN"},{"type":"tableCell","position":{"start":{"line":10,"column":1},"end":{"line":10,"column":1}},"children":[{"type":"text","value":"DFT (PBE/PBE+U)","position":{"start":{"line":10,"column":1},"end":{"line":10,"column":1}},"key":"VCCS7iop5p"}],"key":"JAm29ybaBh"}],"key":"GyeClUMvdi"},{"type":"tableRow","position":{"start":{"line":11,"column":1},"end":{"line":11,"column":1}},"children":[{"type":"tableCell","position":{"start":{"line":11,"column":1},"end":{"line":11,"column":1}},"children":[{"type":"strong","position":{"start":{"line":11,"column":1},"end":{"line":11,"column":1}},"children":[{"type":"text","value":"License","position":{"start":{"line":11,"column":1},"end":{"line":11,"column":1}},"key":"K9TmDoSOyg"}],"key":"GfXPbLsjfq"}],"key":"BOHFswFXfl"},{"type":"tableCell","position":{"start":{"line":11,"column":1},"end":{"line":11,"column":1}},"children":[{"type":"link","url":"https://creativecommons.org/licenses/by/4.0/legalcode","position":{"start":{"line":11,"column":1},"end":{"line":11,"column":1}},"children":[{"type":"text","value":"CC BY 4.0","position":{"start":{"line":11,"column":1},"end":{"line":11,"column":1}},"key":"CUNegGUsBK"}],"urlSource":"https://creativecommons.org/licenses/by/4.0/legalcode","key":"fw1gxqN1CN"}],"key":"jredaLgmit"}],"key":"lPhAk4oFjY"},{"type":"tableRow","position":{"start":{"line":12,"column":1},"end":{"line":12,"column":1}},"children":[{"type":"tableCell","position":{"start":{"line":12,"column":1},"end":{"line":12,"column":1}},"children":[{"type":"strong","position":{"start":{"line":12,"column":1},"end":{"line":12,"column":1}},"children":[{"type":"text","value":"Benchmark","position":{"start":{"line":12,"column":1},"end":{"line":12,"column":1}},"key":"oO2WzHMdnM"}],"key":"bW7pRyg3q0"}],"key":"Ws2MvgELON"},{"type":"tableCell","position":{"start":{"line":12,"column":1},"end":{"line":12,"column":1}},"children":[{"type":"text","value":"Matbench-Discovery compatible","position":{"start":{"line":12,"column":1},"end":{"line":12,"column":1}},"key":"k59EevyABZ"}],"key":"Hse5c18hgu"}],"key":"wWyz8bXmRR"}],"key":"QC1ktb8Ewa"}],"key":"GkHigXGCgQ"},{"type":"paragraph","position":{"start":{"line":15,"column":1},"end":{"line":17,"column":1}},"children":[{"type":"text","value":"The Open Materials 2024 (OMat24) dataset contains a mix of single point calculations of non-equilibrium structures and\nstructural relaxations. The dataset contains structures labeled with total energy (eV), forces (eV/A)\nand stress (eV/A^3). The dataset is provided in ASE DB compatible lmdb files.","position":{"start":{"line":15,"column":1},"end":{"line":15,"column":1}},"key":"dknptl1L1T"}],"key":"mS2N8aKmCY"},{"type":"paragraph","position":{"start":{"line":19,"column":1},"end":{"line":19,"column":1}},"children":[{"type":"text","value":"The OMat24 train and val splits are fully compatible with the Matbench-Discovery benchmark test set.","position":{"start":{"line":19,"column":1},"end":{"line":19,"column":1}},"key":"trU8yJBdng"}],"key":"Q27X349PH0"},{"type":"list","ordered":true,"start":1,"spread":false,"position":{"start":{"line":20,"column":1},"end":{"line":24,"column":1}},"children":[{"type":"listItem","spread":true,"position":{"start":{"line":20,"column":1},"end":{"line":21,"column":1}},"children":[{"type":"paragraph","children":[{"type":"text","value":"The splits do not contain any structure that has a protostructure label present in the initial or relaxed\nstructures of the WBM dataset.","position":{"start":{"line":20,"column":1},"end":{"line":20,"column":1}},"key":"VpIVaQYsv2"}],"key":"U3Yhob9K6j"}],"key":"xNtxO4O0iE"},{"type":"listItem","spread":true,"position":{"start":{"line":22,"column":1},"end":{"line":24,"column":1}},"children":[{"type":"paragraph","children":[{"type":"text","value":"The splits do not include any structure that was generated starting from an Alexandria relaxed structure with\nprotostructure lable in the intitial or relaxed structures of the  WBM datset.","position":{"start":{"line":22,"column":1},"end":{"line":22,"column":1}},"key":"bgIpDwZiXX"}],"key":"LsdfxFWWtm"}],"key":"dAC9gJupQa"}],"key":"RhnTZAFO2g"},{"type":"heading","depth":2,"position":{"start":{"line":25,"column":1},"end":{"line":25,"column":1}},"children":[{"type":"text","value":"Subdatasets","position":{"start":{"line":25,"column":1},"end":{"line":25,"column":1}},"key":"XzVusLK8iu"}],"identifier":"subdatasets","label":"Subdatasets","html_id":"subdatasets","implicit":true,"key":"wdWcJnCkfR"},{"type":"paragraph","position":{"start":{"line":26,"column":1},"end":{"line":26,"column":1}},"children":[{"type":"text","value":"OMat24 is made up of X subdatasets based on how the structures were generated. The subdatasets included are:","position":{"start":{"line":26,"column":1},"end":{"line":26,"column":1}},"key":"sSMSvSBgIV"}],"key":"Hv00u5stvg"},{"type":"list","ordered":true,"start":1,"spread":false,"position":{"start":{"line":27,"column":1},"end":{"line":35,"column":1}},"children":[{"type":"listItem","spread":true,"position":{"start":{"line":27,"column":1},"end":{"line":27,"column":1}},"children":[{"type":"paragraph","children":[{"type":"text","value":"rattled-1000-subsampled & rattled-1000","position":{"start":{"line":27,"column":1},"end":{"line":27,"column":1}},"key":"zbGfnG9u45"}],"key":"qp9Fz79F9L"}],"key":"YSjpAUzZkS"},{"type":"listItem","spread":true,"position":{"start":{"line":28,"column":1},"end":{"line":28,"column":1}},"children":[{"type":"paragraph","children":[{"type":"text","value":"rattled-500-subsampled & rattled-300","position":{"start":{"line":28,"column":1},"end":{"line":28,"column":1}},"key":"qkIYyJdvJZ"}],"key":"PugpmoNj0y"}],"key":"pToJ6zUxVH"},{"type":"listItem","spread":true,"position":{"start":{"line":29,"column":1},"end":{"line":29,"column":1}},"children":[{"type":"paragraph","children":[{"type":"text","value":"rattled-300-subsampled & rattled-500","position":{"start":{"line":29,"column":1},"end":{"line":29,"column":1}},"key":"A37RvTB6VZ"}],"key":"fdt3uy0rXB"}],"key":"NPyg5nt8Jo"},{"type":"listItem","spread":true,"position":{"start":{"line":30,"column":1},"end":{"line":30,"column":1}},"children":[{"type":"paragraph","children":[{"type":"text","value":"aimd-from-PBE-1000-npt","position":{"start":{"line":30,"column":1},"end":{"line":30,"column":1}},"key":"ZJQdiJj4A3"}],"key":"dYuBw3pPYS"}],"key":"ZRiC2rb3GW"},{"type":"listItem","spread":true,"position":{"start":{"line":31,"column":1},"end":{"line":31,"column":1}},"children":[{"type":"paragraph","children":[{"type":"text","value":"aimd-from-PBE-1000-nvt","position":{"start":{"line":31,"column":1},"end":{"line":31,"column":1}},"key":"MMEwlUuGd2"}],"key":"aYpprlEMqQ"}],"key":"PbO7T7yLH4"},{"type":"listItem","spread":true,"position":{"start":{"line":32,"column":1},"end":{"line":32,"column":1}},"children":[{"type":"paragraph","children":[{"type":"text","value":"aimd-from-PBE-3000-npt","position":{"start":{"line":32,"column":1},"end":{"line":32,"column":1}},"key":"ro3JDvh4Iz"}],"key":"PP5vXcyxdY"}],"key":"hOvFdgkhF3"},{"type":"listItem","spread":true,"position":{"start":{"line":33,"column":1},"end":{"line":33,"column":1}},"children":[{"type":"paragraph","children":[{"type":"text","value":"aimd-from-PBE-3000-nvt","position":{"start":{"line":33,"column":1},"end":{"line":33,"column":1}},"key":"xfcVW3h4sy"}],"key":"zTW3UCBDas"}],"key":"hLONnFihy8"},{"type":"listItem","spread":true,"position":{"start":{"line":34,"column":1},"end":{"line":35,"column":1}},"children":[{"type":"paragraph","children":[{"type":"text","value":"rattled-relax","position":{"start":{"line":34,"column":1},"end":{"line":34,"column":1}},"key":"eIzgTW7Cf6"}],"key":"qbCt4U8cZU"}],"key":"TxPMKvTiBa"}],"key":"tKODjl5DiC"},{"type":"paragraph","position":{"start":{"line":36,"column":1},"end":{"line":37,"column":1}},"children":[{"type":"strong","position":{"start":{"line":36,"column":1},"end":{"line":36,"column":1}},"children":[{"type":"text","value":"Note","position":{"start":{"line":36,"column":1},"end":{"line":36,"column":1}},"key":"zUgsgGsmt8"}],"key":"AblOXM8K0H"},{"type":"text","value":" There are two subdatasets for the rattled-< T > datasets. Both subdatasets in each pair were generated with the\nsame procedure as described in our manuscript.","position":{"start":{"line":36,"column":1},"end":{"line":36,"column":1}},"key":"IFzAfMtj3r"}],"key":"ZpKibGw8r0"},{"type":"heading","depth":2,"position":{"start":{"line":39,"column":1},"end":{"line":39,"column":1}},"children":[{"type":"text","value":"File contents and downloads","position":{"start":{"line":39,"column":1},"end":{"line":39,"column":1}},"key":"Zj9naomkfE"}],"identifier":"file-contents-and-downloads","label":"File contents and downloads","html_id":"file-contents-and-downloads","implicit":true,"key":"SD3mnHtDk9"},{"type":"heading","depth":3,"position":{"start":{"line":41,"column":1},"end":{"line":41,"column":1}},"children":[{"type":"text","value":"OMat24 train split","position":{"start":{"line":41,"column":1},"end":{"line":41,"column":1}},"key":"jX0tbuCzsP"}],"identifier":"omat24-train-split","label":"OMat24 train split","html_id":"omat24-train-split","implicit":true,"key":"scPbhrmsZx"},{"type":"table","position":{"start":{"line":42,"column":1},"end":{"line":55,"column":1}},"children":[{"type":"tableRow","position":{"start":{"line":42,"column":1},"end":{"line":42,"column":1}},"children":[{"type":"tableCell","header":true,"align":"center","position":{"start":{"line":42,"column":1},"end":{"line":42,"column":1}},"children":[{"type":"text","value":"Sub-dataset","position":{"start":{"line":42,"column":1},"end":{"line":42,"column":1}},"key":"wR7BYFfUYe"}],"key":"f8aHPpZNh6"},{"type":"tableCell","header":true,"align":"center","position":{"start":{"line":42,"column":1},"end":{"line":42,"column":1}},"children":[{"type":"text","value":"No. structures","position":{"start":{"line":42,"column":1},"end":{"line":42,"column":1}},"key":"ojZSAUkeO9"}],"key":"vFoDkBPFWc"},{"type":"tableCell","header":true,"align":"center","position":{"start":{"line":42,"column":1},"end":{"line":42,"column":1}},"children":[{"type":"text","value":"File size","position":{"start":{"line":42,"column":1},"end":{"line":42,"column":1}},"key":"wTVZO8pub9"}],"key":"wdr5W2sy21"},{"type":"tableCell","header":true,"align":"center","position":{"start":{"line":42,"column":1},"end":{"line":42,"column":1}},"children":[{"type":"text","value":"Download","position":{"start":{"line":42,"column":1},"end":{"line":42,"column":1}},"key":"Hytb1I1rAT"}],"key":"Sh0O857Ax4"}],"key":"WTqzg5x1le"},{"type":"tableRow","position":{"start":{"line":44,"column":1},"end":{"line":44,"column":1}},"children":[{"type":"tableCell","align":"center","position":{"start":{"line":44,"column":1},"end":{"line":44,"column":1}},"children":[{"type":"text","value":"rattled-1000","position":{"start":{"line":44,"column":1},"end":{"line":44,"column":1}},"key":"pbDzN2erxs"}],"key":"MTboNEs0Gq"},{"type":"tableCell","align":"center","position":{"start":{"line":44,"column":1},"end":{"line":44,"column":1}},"children":[{"type":"text","value":"122,937","position":{"start":{"line":44,"column":1},"end":{"line":44,"column":1}},"key":"mQGtGTlHLi"}],"key":"QkVywqC1pc"},{"type":"tableCell","align":"center","position":{"start":{"line":44,"column":1},"end":{"line":44,"column":1}},"children":[{"type":"text","value":"21 GB","position":{"start":{"line":44,"column":1},"end":{"line":44,"column":1}},"key":"YUhkWPjj8L"}],"key":"p3tBRvHNL1"},{"type":"tableCell","align":"center","position":{"start":{"line":44,"column":1},"end":{"line":44,"column":1}},"children":[{"type":"link","url":"https://dl.fbaipublicfiles.com/opencatalystproject/data/omat/241018/omat/train/rattled-1000.tar.gz","position":{"start":{"line":44,"column":1},"end":{"line":44,"column":1}},"children":[{"type":"text","value":"rattled-1000.tar.gz","position":{"start":{"line":44,"column":1},"end":{"line":44,"column":1}},"key":"dddsSqduh0"}],"urlSource":"https://dl.fbaipublicfiles.com/opencatalystproject/data/omat/241018/omat/train/rattled-1000.tar.gz","key":"mNWla1VnyU"}],"key":"rOLnaepzvD"}],"key":"LSATcw4vUz"},{"type":"tableRow","position":{"start":{"line":45,"column":1},"end":{"line":45,"column":1}},"children":[{"type":"tableCell","align":"center","position":{"start":{"line":45,"column":1},"end":{"line":45,"column":1}},"children":[{"type":"text","value":"rattled-1000-subsampled","position":{"start":{"line":45,"column":1},"end":{"line":45,"column":1}},"key":"frqBLvSTvl"}],"key":"WhizkaXlPw"},{"type":"tableCell","align":"center","position":{"start":{"line":45,"column":1},"end":{"line":45,"column":1}},"children":[{"type":"text","value":"41,786","position":{"start":{"line":45,"column":1},"end":{"line":45,"column":1}},"key":"VdRMkiX9I5"}],"key":"UZyNSESH69"},{"type":"tableCell","align":"center","position":{"start":{"line":45,"column":1},"end":{"line":45,"column":1}},"children":[{"type":"text","value":"7.1 GB","position":{"start":{"line":45,"column":1},"end":{"line":45,"column":1}},"key":"dKfzPoSpZ0"}],"key":"UgGEWcWaGr"},{"type":"tableCell","align":"center","position":{"start":{"line":45,"column":1},"end":{"line":45,"column":1}},"children":[{"type":"link","url":"https://dl.fbaipublicfiles.com/opencatalystproject/data/omat/241018/omat/train/rattled-1000-subsampled.tar.gz","position":{"start":{"line":45,"column":1},"end":{"line":45,"column":1}},"children":[{"type":"text","value":"rattled​-1000​-subsampled​.tar​.gz","position":{"start":{"line":45,"column":1},"end":{"line":45,"column":1}},"key":"XPSIvXn2du"}],"urlSource":"https://dl.fbaipublicfiles.com/opencatalystproject/data/omat/241018/omat/train/rattled-1000-subsampled.tar.gz","key":"FGyMXGRaip"}],"key":"fq7c8NsLtA"}],"key":"pFPJyPuu9y"},{"type":"tableRow","position":{"start":{"line":46,"column":1},"end":{"line":46,"column":1}},"children":[{"type":"tableCell","align":"center","position":{"start":{"line":46,"column":1},"end":{"line":46,"column":1}},"children":[{"type":"text","value":"rattled-500","position":{"start":{"line":46,"column":1},"end":{"line":46,"column":1}},"key":"hQMjam3C1f"}],"key":"oMDQRNbORD"},{"type":"tableCell","align":"center","position":{"start":{"line":46,"column":1},"end":{"line":46,"column":1}},"children":[{"type":"text","value":"75,167","position":{"start":{"line":46,"column":1},"end":{"line":46,"column":1}},"key":"XO2ssiwg6S"}],"key":"bPRz56dqch"},{"type":"tableCell","align":"center","position":{"start":{"line":46,"column":1},"end":{"line":46,"column":1}},"children":[{"type":"text","value":"13 GB","position":{"start":{"line":46,"column":1},"end":{"line":46,"column":1}},"key":"we9Xf9OpOu"}],"key":"bpMm684lxA"},{"type":"tableCell","align":"center","position":{"start":{"line":46,"column":1},"end":{"line":46,"column":1}},"children":[{"type":"link","url":"https://dl.fbaipublicfiles.com/opencatalystproject/data/omat/241018/omat/train/rattled-500.tar.gz","position":{"start":{"line":46,"column":1},"end":{"line":46,"column":1}},"children":[{"type":"text","value":"rattled-500.tar.gz","position":{"start":{"line":46,"column":1},"end":{"line":46,"column":1}},"key":"ruvMcMaul3"}],"urlSource":"https://dl.fbaipublicfiles.com/opencatalystproject/data/omat/241018/omat/train/rattled-500.tar.gz","key":"UKn8f7U6vl"}],"key":"cStajgxlmi"}],"key":"uc7MO4IXTe"},{"type":"tableRow","position":{"start":{"line":47,"column":1},"end":{"line":47,"column":1}},"children":[{"type":"tableCell","align":"center","position":{"start":{"line":47,"column":1},"end":{"line":47,"column":1}},"children":[{"type":"text","value":"rattled-500-subsampled","position":{"start":{"line":47,"column":1},"end":{"line":47,"column":1}},"key":"qwlfrRQoHk"}],"key":"GQmxQRtsap"},{"type":"tableCell","align":"center","position":{"start":{"line":47,"column":1},"end":{"line":47,"column":1}},"children":[{"type":"text","value":"43,068","position":{"start":{"line":47,"column":1},"end":{"line":47,"column":1}},"key":"yLzvFJEfYP"}],"key":"dETYFxaIDp"},{"type":"tableCell","align":"center","position":{"start":{"line":47,"column":1},"end":{"line":47,"column":1}},"children":[{"type":"text","value":"7.3 GB","position":{"start":{"line":47,"column":1},"end":{"line":47,"column":1}},"key":"w69bP9JD1h"}],"key":"BW1PClbLzc"},{"type":"tableCell","align":"center","position":{"start":{"line":47,"column":1},"end":{"line":47,"column":1}},"children":[{"type":"link","url":"https://dl.fbaipublicfiles.com/opencatalystproject/data/omat/241018/omat/train/rattled-500-subsampled.tar.gz","position":{"start":{"line":47,"column":1},"end":{"line":47,"column":1}},"children":[{"type":"text","value":"rattled​-500​-subsampled​.tar​.gz","position":{"start":{"line":47,"column":1},"end":{"line":47,"column":1}},"key":"v680PnuHnZ"}],"urlSource":"https://dl.fbaipublicfiles.com/opencatalystproject/data/omat/241018/omat/train/rattled-500-subsampled.tar.gz","key":"QgBgruOZLc"}],"key":"IGLABLYkwx"}],"key":"erD1rEP9vu"},{"type":"tableRow","position":{"start":{"line":48,"column":1},"end":{"line":48,"column":1}},"children":[{"type":"tableCell","align":"center","position":{"start":{"line":48,"column":1},"end":{"line":48,"column":1}},"children":[{"type":"text","value":"rattled-300","position":{"start":{"line":48,"column":1},"end":{"line":48,"column":1}},"key":"ZbCydA04Rx"}],"key":"QCK1sk3Nk6"},{"type":"tableCell","align":"center","position":{"start":{"line":48,"column":1},"end":{"line":48,"column":1}},"children":[{"type":"text","value":"68,593","position":{"start":{"line":48,"column":1},"end":{"line":48,"column":1}},"key":"P7U3v4CGc9"}],"key":"MLMA34BhnK"},{"type":"tableCell","align":"center","position":{"start":{"line":48,"column":1},"end":{"line":48,"column":1}},"children":[{"type":"text","value":"12 GB","position":{"start":{"line":48,"column":1},"end":{"line":48,"column":1}},"key":"fJkKndaKJ8"}],"key":"qp8Usunqz1"},{"type":"tableCell","align":"center","position":{"start":{"line":48,"column":1},"end":{"line":48,"column":1}},"children":[{"type":"link","url":"https://dl.fbaipublicfiles.com/opencatalystproject/data/omat/241018/omat/train/rattled-300.tar.gz","position":{"start":{"line":48,"column":1},"end":{"line":48,"column":1}},"children":[{"type":"text","value":"rattled-300.tar.gz","position":{"start":{"line":48,"column":1},"end":{"line":48,"column":1}},"key":"StLMqlo7Nr"}],"urlSource":"https://dl.fbaipublicfiles.com/opencatalystproject/data/omat/241018/omat/train/rattled-300.tar.gz","key":"K6xRygTkPZ"}],"key":"yiCmeQugmo"}],"key":"ZYS0PTdtvE"},{"type":"tableRow","position":{"start":{"line":49,"column":1},"end":{"line":49,"column":1}},"children":[{"type":"tableCell","align":"center","position":{"start":{"line":49,"column":1},"end":{"line":49,"column":1}},"children":[{"type":"text","value":"rattled-300-subsampled","position":{"start":{"line":49,"column":1},"end":{"line":49,"column":1}},"key":"JLBuqiRa4U"}],"key":"OiHgYWZAyw"},{"type":"tableCell","align":"center","position":{"start":{"line":49,"column":1},"end":{"line":49,"column":1}},"children":[{"type":"text","value":"37,393","position":{"start":{"line":49,"column":1},"end":{"line":49,"column":1}},"key":"yzh9VnbRkf"}],"key":"hpTd9PeFcC"},{"type":"tableCell","align":"center","position":{"start":{"line":49,"column":1},"end":{"line":49,"column":1}},"children":[{"type":"text","value":"6.4 GB","position":{"start":{"line":49,"column":1},"end":{"line":49,"column":1}},"key":"fvjOZIxueJ"}],"key":"mGQS6KQt73"},{"type":"tableCell","align":"center","position":{"start":{"line":49,"column":1},"end":{"line":49,"column":1}},"children":[{"type":"link","url":"https://dl.fbaipublicfiles.com/opencatalystproject/data/omat/241018/omat/train/rattled-300-subsampled.tar.gz","position":{"start":{"line":49,"column":1},"end":{"line":49,"column":1}},"children":[{"type":"text","value":"rattled​-300​-subsampled​.tar​.gz","position":{"start":{"line":49,"column":1},"end":{"line":49,"column":1}},"key":"OdF6BzoPle"}],"urlSource":"https://dl.fbaipublicfiles.com/opencatalystproject/data/omat/241018/omat/train/rattled-300-subsampled.tar.gz","key":"Kzrts2komu"}],"key":"HoOmihai6h"}],"key":"eLx56ygMF1"},{"type":"tableRow","position":{"start":{"line":50,"column":1},"end":{"line":50,"column":1}},"children":[{"type":"tableCell","align":"center","position":{"start":{"line":50,"column":1},"end":{"line":50,"column":1}},"children":[{"type":"text","value":"aimd-from-PBE-1000-npt","position":{"start":{"line":50,"column":1},"end":{"line":50,"column":1}},"key":"TCM6D29FD8"}],"key":"XtsAx7leOQ"},{"type":"tableCell","align":"center","position":{"start":{"line":50,"column":1},"end":{"line":50,"column":1}},"children":[{"type":"text","value":"223,574","position":{"start":{"line":50,"column":1},"end":{"line":50,"column":1}},"key":"uff50yGPPi"}],"key":"LS3zFhlEcU"},{"type":"tableCell","align":"center","position":{"start":{"line":50,"column":1},"end":{"line":50,"column":1}},"children":[{"type":"text","value":"26 GB","position":{"start":{"line":50,"column":1},"end":{"line":50,"column":1}},"key":"gZ6ThcvRs7"}],"key":"RJbSsAXCso"},{"type":"tableCell","align":"center","position":{"start":{"line":50,"column":1},"end":{"line":50,"column":1}},"children":[{"type":"link","url":"https://dl.fbaipublicfiles.com/opencatalystproject/data/omat/241018/omat/train/aimd-from-PBE-1000-npt.tar.gz","position":{"start":{"line":50,"column":1},"end":{"line":50,"column":1}},"children":[{"type":"text","value":"aimd​-from​-PBE​-1000​-npt​.tar​.gz","position":{"start":{"line":50,"column":1},"end":{"line":50,"column":1}},"key":"GFcDzfbuXG"}],"urlSource":"https://dl.fbaipublicfiles.com/opencatalystproject/data/omat/241018/omat/train/aimd-from-PBE-1000-npt.tar.gz","key":"aMrhE4cAVZ"}],"key":"fK0pg1mliw"}],"key":"BQsADmfR2B"},{"type":"tableRow","position":{"start":{"line":51,"column":1},"end":{"line":51,"column":1}},"children":[{"type":"tableCell","align":"center","position":{"start":{"line":51,"column":1},"end":{"line":51,"column":1}},"children":[{"type":"text","value":"aimd-from-PBE-1000-nvt","position":{"start":{"line":51,"column":1},"end":{"line":51,"column":1}},"key":"LNcxO6I2UI"}],"key":"VEb5bFkgwI"},{"type":"tableCell","align":"center","position":{"start":{"line":51,"column":1},"end":{"line":51,"column":1}},"children":[{"type":"text","value":"215,589","position":{"start":{"line":51,"column":1},"end":{"line":51,"column":1}},"key":"a5ApyO0tli"}],"key":"JHvgAr7qR2"},{"type":"tableCell","align":"center","position":{"start":{"line":51,"column":1},"end":{"line":51,"column":1}},"children":[{"type":"text","value":"24 GB","position":{"start":{"line":51,"column":1},"end":{"line":51,"column":1}},"key":"bfKLHF0OFG"}],"key":"XnXmuKg2s0"},{"type":"tableCell","align":"center","position":{"start":{"line":51,"column":1},"end":{"line":51,"column":1}},"children":[{"type":"link","url":"https://dl.fbaipublicfiles.com/opencatalystproject/data/omat/241018/omat/train/aimd-from-PBE-1000-nvt.tar.gz","position":{"start":{"line":51,"column":1},"end":{"line":51,"column":1}},"children":[{"type":"text","value":"aimd​-from​-PBE​-1000​-nvt​.tar​.gz","position":{"start":{"line":51,"column":1},"end":{"line":51,"column":1}},"key":"h4nKmynpr5"}],"urlSource":"https://dl.fbaipublicfiles.com/opencatalystproject/data/omat/241018/omat/train/aimd-from-PBE-1000-nvt.tar.gz","key":"lmnx5KfJ8G"}],"key":"EsZvUOKSLG"}],"key":"pWZwxXq02f"},{"type":"tableRow","position":{"start":{"line":52,"column":1},"end":{"line":52,"column":1}},"children":[{"type":"tableCell","align":"center","position":{"start":{"line":52,"column":1},"end":{"line":52,"column":1}},"children":[{"type":"text","value":"aimd-from-PBE-3000-npt","position":{"start":{"line":52,"column":1},"end":{"line":52,"column":1}},"key":"rLMvzQxBTv"}],"key":"BGKvFDVsSo"},{"type":"tableCell","align":"center","position":{"start":{"line":52,"column":1},"end":{"line":52,"column":1}},"children":[{"type":"text","value":"65,244","position":{"start":{"line":52,"column":1},"end":{"line":52,"column":1}},"key":"ic2yKoeNL5"}],"key":"jgrajaILQ8"},{"type":"tableCell","align":"center","position":{"start":{"line":52,"column":1},"end":{"line":52,"column":1}},"children":[{"type":"text","value":"25 GB","position":{"start":{"line":52,"column":1},"end":{"line":52,"column":1}},"key":"TDr9eQogon"}],"key":"VyTheJ3Xe5"},{"type":"tableCell","align":"center","position":{"start":{"line":52,"column":1},"end":{"line":52,"column":1}},"children":[{"type":"link","url":"https://dl.fbaipublicfiles.com/opencatalystproject/data/omat/241018/omat/train/aimd-from-PBE-3000-npt.tar.gz","position":{"start":{"line":52,"column":1},"end":{"line":52,"column":1}},"children":[{"type":"text","value":"aimd​-from​-PBE​-3000​-npt​.tar​.gz","position":{"start":{"line":52,"column":1},"end":{"line":52,"column":1}},"key":"wfFC5IxUUj"}],"urlSource":"https://dl.fbaipublicfiles.com/opencatalystproject/data/omat/241018/omat/train/aimd-from-PBE-3000-npt.tar.gz","key":"uMzx2zhDoc"}],"key":"doxc4DuaUV"}],"key":"nlzIOIQd8R"},{"type":"tableRow","position":{"start":{"line":53,"column":1},"end":{"line":53,"column":1}},"children":[{"type":"tableCell","align":"center","position":{"start":{"line":53,"column":1},"end":{"line":53,"column":1}},"children":[{"type":"text","value":"aimd-from-PBE-3000-nvt","position":{"start":{"line":53,"column":1},"end":{"line":53,"column":1}},"key":"V5X7SavweT"}],"key":"U67PkLgsZz"},{"type":"tableCell","align":"center","position":{"start":{"line":53,"column":1},"end":{"line":53,"column":1}},"children":[{"type":"text","value":"84,063","position":{"start":{"line":53,"column":1},"end":{"line":53,"column":1}},"key":"uFVRYNlyUW"}],"key":"hyS4yNWx1c"},{"type":"tableCell","align":"center","position":{"start":{"line":53,"column":1},"end":{"line":53,"column":1}},"children":[{"type":"text","value":"32 GB","position":{"start":{"line":53,"column":1},"end":{"line":53,"column":1}},"key":"Y1gZbQH8o4"}],"key":"cjfFq8Rlvb"},{"type":"tableCell","align":"center","position":{"start":{"line":53,"column":1},"end":{"line":53,"column":1}},"children":[{"type":"link","url":"https://dl.fbaipublicfiles.com/opencatalystproject/data/omat/241018/omat/train/aimd-from-PBE-3000-nvt.tar.gz","position":{"start":{"line":53,"column":1},"end":{"line":53,"column":1}},"children":[{"type":"text","value":"aimd​-from​-PBE​-3000​-nvt​.tar​.gz","position":{"start":{"line":53,"column":1},"end":{"line":53,"column":1}},"key":"ZsFpytW4vP"}],"urlSource":"https://dl.fbaipublicfiles.com/opencatalystproject/data/omat/241018/omat/train/aimd-from-PBE-3000-nvt.tar.gz","key":"V2xTxEOhwi"}],"key":"ePrYWS9SeZ"}],"key":"MFZ0AAcN1V"},{"type":"tableRow","position":{"start":{"line":54,"column":1},"end":{"line":54,"column":1}},"children":[{"type":"tableCell","align":"center","position":{"start":{"line":54,"column":1},"end":{"line":54,"column":1}},"children":[{"type":"text","value":"rattled-relax","position":{"start":{"line":54,"column":1},"end":{"line":54,"column":1}},"key":"safMiFXL6p"}],"key":"A7h5xP23aB"},{"type":"tableCell","align":"center","position":{"start":{"line":54,"column":1},"end":{"line":54,"column":1}},"children":[{"type":"text","value":"99,968","position":{"start":{"line":54,"column":1},"end":{"line":54,"column":1}},"key":"GFg6qkFPXo"}],"key":"iRvCeFCU0f"},{"type":"tableCell","align":"center","position":{"start":{"line":54,"column":1},"end":{"line":54,"column":1}},"children":[{"type":"text","value":"12 GB","position":{"start":{"line":54,"column":1},"end":{"line":54,"column":1}},"key":"ihbuVz2IKz"}],"key":"QRhK9XiGK7"},{"type":"tableCell","align":"center","position":{"start":{"line":54,"column":1},"end":{"line":54,"column":1}},"children":[{"type":"link","url":"https://dl.fbaipublicfiles.com/opencatalystproject/data/omat/241018/omat/train/rattled-relax.tar.gz","position":{"start":{"line":54,"column":1},"end":{"line":54,"column":1}},"children":[{"type":"text","value":"rattled​-relax​.tar​.gz","position":{"start":{"line":54,"column":1},"end":{"line":54,"column":1}},"key":"pfEnf0iFnL"}],"urlSource":"https://dl.fbaipublicfiles.com/opencatalystproject/data/omat/241018/omat/train/rattled-relax.tar.gz","key":"fARCAmR2SY"}],"key":"KonYCc6zU8"}],"key":"aH6T6tuQhx"},{"type":"tableRow","position":{"start":{"line":55,"column":1},"end":{"line":55,"column":1}},"children":[{"type":"tableCell","align":"center","position":{"start":{"line":55,"column":1},"end":{"line":55,"column":1}},"children":[{"type":"text","value":"Total","position":{"start":{"line":55,"column":1},"end":{"line":55,"column":1}},"key":"lOOvUDex8U"}],"key":"YYDaijuIO0"},{"type":"tableCell","align":"center","position":{"start":{"line":55,"column":1},"end":{"line":55,"column":1}},"children":[{"type":"text","value":"1,077,382","position":{"start":{"line":55,"column":1},"end":{"line":55,"column":1}},"key":"o4bsNLXdrQ"}],"key":"fqBrXneZkT"},{"type":"tableCell","align":"center","position":{"start":{"line":55,"column":1},"end":{"line":55,"column":1}},"children":[{"type":"text","value":"185.8 GB","position":{"start":{"line":55,"column":1},"end":{"line":55,"column":1}},"key":"GjwW6QZtLt"}],"key":"M6XikG7EPy"},{"type":"tableCell","align":"center","position":{"start":{"line":55,"column":1},"end":{"line":55,"column":1}},"children":[],"key":"av3gluQJrN"}],"key":"Uwr8MVPkpg"}],"key":"wWBHlrocLu"},{"type":"heading","depth":3,"position":{"start":{"line":57,"column":1},"end":{"line":57,"column":1}},"children":[{"type":"text","value":"OMat24 val split (this is a 1M subset used to train eqV2 models from the 5M val split)","position":{"start":{"line":57,"column":1},"end":{"line":57,"column":1}},"key":"hhd4njDIuw"}],"identifier":"omat24-val-split-this-is-a-1m-subset-used-to-train-eqv2-models-from-the-5m-val-split","label":"OMat24 val split (this is a 1M subset used to train eqV2 models from the 5M val split)","html_id":"omat24-val-split-this-is-a-1m-subset-used-to-train-eqv2-models-from-the-5m-val-split","implicit":true,"key":"Zd5kFsfakn"},{"type":"paragraph","position":{"start":{"line":58,"column":1},"end":{"line":59,"column":1}},"children":[{"type":"strong","position":{"start":{"line":58,"column":1},"end":{"line":58,"column":1}},"children":[{"type":"emphasis","position":{"start":{"line":58,"column":1},"end":{"line":58,"column":1}},"children":[{"type":"text","value":"NOTE:","position":{"start":{"line":58,"column":1},"end":{"line":58,"column":1}},"key":"jGFkgQk1Lp"}],"key":"MWr37yoV7F"}],"key":"hnh7z0x4mV"},{"type":"text","value":" The original validation sets contained a duplicated structures. Corrected validation sets were uploaded on 20/12/24. Please see this ","position":{"start":{"line":58,"column":1},"end":{"line":58,"column":1}},"key":"PqpW2cg0qJ"},{"type":"link","url":"https://github.com/facebookresearch/fairchem/issues/942","position":{"start":{"line":58,"column":1},"end":{"line":58,"column":1}},"children":[{"type":"text","value":"issue","position":{"start":{"line":58,"column":1},"end":{"line":58,"column":1}},"key":"nqSqAX74T6"}],"urlSource":"https://github.com/facebookresearch/fairchem/issues/942","data":{"kind":"issue","org":"facebookresearch","repo":"fairchem","issue_number":"942"},"internal":false,"protocol":"github","key":"ULAfW6ysrX"},{"type":"text","value":"\nfor more details, an re-download the correct version of the validation sets if needed.","position":{"start":{"line":58,"column":1},"end":{"line":58,"column":1}},"key":"SjPGcXsBTo"}],"key":"sib9qQGtx2"},{"type":"table","position":{"start":{"line":61,"column":1},"end":{"line":74,"column":1}},"children":[{"type":"tableRow","position":{"start":{"line":61,"column":1},"end":{"line":61,"column":1}},"children":[{"type":"tableCell","header":true,"align":"center","position":{"start":{"line":61,"column":1},"end":{"line":61,"column":1}},"children":[{"type":"text","value":"Sub-dataset","position":{"start":{"line":61,"column":1},"end":{"line":61,"column":1}},"key":"B1GyHxTfFg"}],"key":"zH4T1y05eV"},{"type":"tableCell","header":true,"align":"center","position":{"start":{"line":61,"column":1},"end":{"line":61,"column":1}},"children":[{"type":"text","value":"Size","position":{"start":{"line":61,"column":1},"end":{"line":61,"column":1}},"key":"UiYqK99Yq0"}],"key":"TaIOgiQJx4"},{"type":"tableCell","header":true,"align":"center","position":{"start":{"line":61,"column":1},"end":{"line":61,"column":1}},"children":[{"type":"text","value":"File Size","position":{"start":{"line":61,"column":1},"end":{"line":61,"column":1}},"key":"znaoN6mieG"}],"key":"Kc0TtZrVRz"},{"type":"tableCell","header":true,"align":"right","position":{"start":{"line":61,"column":1},"end":{"line":61,"column":1}},"children":[{"type":"text","value":"Download","position":{"start":{"line":61,"column":1},"end":{"line":61,"column":1}},"key":"T4XCxKIIir"}],"key":"ml18pPcjqC"}],"key":"syZi440wmF"},{"type":"tableRow","position":{"start":{"line":63,"column":1},"end":{"line":63,"column":1}},"children":[{"type":"tableCell","align":"center","position":{"start":{"line":63,"column":1},"end":{"line":63,"column":1}},"children":[{"type":"text","value":"rattled-1000","position":{"start":{"line":63,"column":1},"end":{"line":63,"column":1}},"key":"W9GHAlUVAR"}],"key":"dZVB2nWbc1"},{"type":"tableCell","align":"center","position":{"start":{"line":63,"column":1},"end":{"line":63,"column":1}},"children":[{"type":"text","value":"117,004","position":{"start":{"line":63,"column":1},"end":{"line":63,"column":1}},"key":"RSlg1SXR9S"}],"key":"ayGmVk47Yz"},{"type":"tableCell","align":"center","position":{"start":{"line":63,"column":1},"end":{"line":63,"column":1}},"children":[{"type":"text","value":"218 MB","position":{"start":{"line":63,"column":1},"end":{"line":63,"column":1}},"key":"lJ7MI1YUxf"}],"key":"qiwlU0ky1t"},{"type":"tableCell","align":"right","position":{"start":{"line":63,"column":1},"end":{"line":63,"column":1}},"children":[{"type":"link","url":"https://dl.fbaipublicfiles.com/opencatalystproject/data/omat/241220/omat/val/rattled-1000.tar.gz","position":{"start":{"line":63,"column":1},"end":{"line":63,"column":1}},"children":[{"type":"text","value":"rattled-1000.tar.gz","position":{"start":{"line":63,"column":1},"end":{"line":63,"column":1}},"key":"K1vBDPbPYl"}],"urlSource":"https://dl.fbaipublicfiles.com/opencatalystproject/data/omat/241220/omat/val/rattled-1000.tar.gz","key":"rCJ4xWuSAq"}],"key":"U2N5C1jObd"}],"key":"XHwR7qhCYp"},{"type":"tableRow","position":{"start":{"line":64,"column":1},"end":{"line":64,"column":1}},"children":[{"type":"tableCell","align":"center","position":{"start":{"line":64,"column":1},"end":{"line":64,"column":1}},"children":[{"type":"text","value":"rattled-1000-subsampled","position":{"start":{"line":64,"column":1},"end":{"line":64,"column":1}},"key":"o78R69ZWYk"}],"key":"FRbAgJbJco"},{"type":"tableCell","align":"center","position":{"start":{"line":64,"column":1},"end":{"line":64,"column":1}},"children":[{"type":"text","value":"39,785","position":{"start":{"line":64,"column":1},"end":{"line":64,"column":1}},"key":"TFmxWfJU7b"}],"key":"abyb67wUlR"},{"type":"tableCell","align":"center","position":{"start":{"line":64,"column":1},"end":{"line":64,"column":1}},"children":[{"type":"text","value":"77 MB","position":{"start":{"line":64,"column":1},"end":{"line":64,"column":1}},"key":"NmEGJNlwmD"}],"key":"JZyC5c0vIO"},{"type":"tableCell","align":"right","position":{"start":{"line":64,"column":1},"end":{"line":64,"column":1}},"children":[{"type":"link","url":"https://dl.fbaipublicfiles.com/opencatalystproject/data/omat/241220/omat/val/rattled-1000-subsampled.tar.gz","position":{"start":{"line":64,"column":1},"end":{"line":64,"column":1}},"children":[{"type":"text","value":"rattled​-1000​-subsampled​.tar​.gz","position":{"start":{"line":64,"column":1},"end":{"line":64,"column":1}},"key":"icsrHc5q09"}],"urlSource":"https://dl.fbaipublicfiles.com/opencatalystproject/data/omat/241220/omat/val/rattled-1000-subsampled.tar.gz","key":"WnKwCZPpC6"}],"key":"hzIXO0vSni"}],"key":"jX36Djqrrt"},{"type":"tableRow","position":{"start":{"line":65,"column":1},"end":{"line":65,"column":1}},"children":[{"type":"tableCell","align":"center","position":{"start":{"line":65,"column":1},"end":{"line":65,"column":1}},"children":[{"type":"text","value":"rattled-500","position":{"start":{"line":65,"column":1},"end":{"line":65,"column":1}},"key":"PsF73eSF6o"}],"key":"GnuYkSlGr7"},{"type":"tableCell","align":"center","position":{"start":{"line":65,"column":1},"end":{"line":65,"column":1}},"children":[{"type":"text","value":"71,522","position":{"start":{"line":65,"column":1},"end":{"line":65,"column":1}},"key":"YaQdlX2kPc"}],"key":"M8O6jRIZ0p"},{"type":"tableCell","align":"center","position":{"start":{"line":65,"column":1},"end":{"line":65,"column":1}},"children":[{"type":"text","value":"135 MB","position":{"start":{"line":65,"column":1},"end":{"line":65,"column":1}},"key":"MKtyRLVZYT"}],"key":"hLsU6UMkBq"},{"type":"tableCell","align":"right","position":{"start":{"line":65,"column":1},"end":{"line":65,"column":1}},"children":[{"type":"link","url":"https://dl.fbaipublicfiles.com/opencatalystproject/data/omat/241220/omat/val/rattled-500.tar.gz","position":{"start":{"line":65,"column":1},"end":{"line":65,"column":1}},"children":[{"type":"text","value":"rattled-500.tar.gz","position":{"start":{"line":65,"column":1},"end":{"line":65,"column":1}},"key":"vlwMHdqVeT"}],"urlSource":"https://dl.fbaipublicfiles.com/opencatalystproject/data/omat/241220/omat/val/rattled-500.tar.gz","key":"inJMGz9QuY"}],"key":"riPXPz0eeh"}],"key":"kSmetB9ytK"},{"type":"tableRow","position":{"start":{"line":66,"column":1},"end":{"line":66,"column":1}},"children":[{"type":"tableCell","align":"center","position":{"start":{"line":66,"column":1},"end":{"line":66,"column":1}},"children":[{"type":"text","value":"rattled-500-subsampled","position":{"start":{"line":66,"column":1},"end":{"line":66,"column":1}},"key":"V00xWc4jkI"}],"key":"HNWpbJ2lIu"},{"type":"tableCell","align":"center","position":{"start":{"line":66,"column":1},"end":{"line":66,"column":1}},"children":[{"type":"text","value":"41,021","position":{"start":{"line":66,"column":1},"end":{"line":66,"column":1}},"key":"l9jrBvwhbf"}],"key":"bSUGYvuEoo"},{"type":"tableCell","align":"center","position":{"start":{"line":66,"column":1},"end":{"line":66,"column":1}},"children":[{"type":"text","value":"79 MB","position":{"start":{"line":66,"column":1},"end":{"line":66,"column":1}},"key":"B1YC6xceWL"}],"key":"UJveF2xOUJ"},{"type":"tableCell","align":"right","position":{"start":{"line":66,"column":1},"end":{"line":66,"column":1}},"children":[{"type":"link","url":"https://dl.fbaipublicfiles.com/opencatalystproject/data/omat/241220/omat/val/rattled-500-subsampled.tar.gz","position":{"start":{"line":66,"column":1},"end":{"line":66,"column":1}},"children":[{"type":"text","value":"rattled​-500​-subsampled​.tar​.gz","position":{"start":{"line":66,"column":1},"end":{"line":66,"column":1}},"key":"Ihk6x3kTAe"}],"urlSource":"https://dl.fbaipublicfiles.com/opencatalystproject/data/omat/241220/omat/val/rattled-500-subsampled.tar.gz","key":"z6UJTThDKZ"}],"key":"en9AXjCwRk"}],"key":"ODWNheF7U7"},{"type":"tableRow","position":{"start":{"line":67,"column":1},"end":{"line":67,"column":1}},"children":[{"type":"tableCell","align":"center","position":{"start":{"line":67,"column":1},"end":{"line":67,"column":1}},"children":[{"type":"text","value":"rattled-300","position":{"start":{"line":67,"column":1},"end":{"line":67,"column":1}},"key":"CTaKD7BELn"}],"key":"QM0p9HGC18"},{"type":"tableCell","align":"center","position":{"start":{"line":67,"column":1},"end":{"line":67,"column":1}},"children":[{"type":"text","value":"65,235","position":{"start":{"line":67,"column":1},"end":{"line":67,"column":1}},"key":"SePZpCycwA"}],"key":"GerN7BFGgf"},{"type":"tableCell","align":"center","position":{"start":{"line":67,"column":1},"end":{"line":67,"column":1}},"children":[{"type":"text","value":"122 MB","position":{"start":{"line":67,"column":1},"end":{"line":67,"column":1}},"key":"ZhBFLDVl6I"}],"key":"DOZwEUQyiP"},{"type":"tableCell","align":"right","position":{"start":{"line":67,"column":1},"end":{"line":67,"column":1}},"children":[{"type":"link","url":"https://dl.fbaipublicfiles.com/opencatalystproject/data/omat/241220/omat/val/rattled-300.tar.gz","position":{"start":{"line":67,"column":1},"end":{"line":67,"column":1}},"children":[{"type":"text","value":"rattled-300.tar.gz","position":{"start":{"line":67,"column":1},"end":{"line":67,"column":1}},"key":"WYxTt10IqX"}],"urlSource":"https://dl.fbaipublicfiles.com/opencatalystproject/data/omat/241220/omat/val/rattled-300.tar.gz","key":"mwWvtrM5GP"}],"key":"GzWMUl5Z6t"}],"key":"jsmfrHurNC"},{"type":"tableRow","position":{"start":{"line":68,"column":1},"end":{"line":68,"column":1}},"children":[{"type":"tableCell","align":"center","position":{"start":{"line":68,"column":1},"end":{"line":68,"column":1}},"children":[{"type":"text","value":"rattled-300-subsampled","position":{"start":{"line":68,"column":1},"end":{"line":68,"column":1}},"key":"UMyQ5NTBKs"}],"key":"tU7nEGwVQg"},{"type":"tableCell","align":"center","position":{"start":{"line":68,"column":1},"end":{"line":68,"column":1}},"children":[{"type":"text","value":"35,579","position":{"start":{"line":68,"column":1},"end":{"line":68,"column":1}},"key":"fm6XyRAcFO"}],"key":"YqElhRiNW5"},{"type":"tableCell","align":"center","position":{"start":{"line":68,"column":1},"end":{"line":68,"column":1}},"children":[{"type":"text","value":"69 MB","position":{"start":{"line":68,"column":1},"end":{"line":68,"column":1}},"key":"BfLAP6LyrN"}],"key":"mJVG8c06TZ"},{"type":"tableCell","align":"right","position":{"start":{"line":68,"column":1},"end":{"line":68,"column":1}},"children":[{"type":"link","url":"https://dl.fbaipublicfiles.com/opencatalystproject/data/omat/241220/omat/val/rattled-300-subsampled.tar.gz","position":{"start":{"line":68,"column":1},"end":{"line":68,"column":1}},"children":[{"type":"text","value":"rattled​-300​-subsampled​.tar​.gz","position":{"start":{"line":68,"column":1},"end":{"line":68,"column":1}},"key":"Nr7KANbddU"}],"urlSource":"https://dl.fbaipublicfiles.com/opencatalystproject/data/omat/241220/omat/val/rattled-300-subsampled.tar.gz","key":"u0pLXUO03Y"}],"key":"ylCWdFSK6D"}],"key":"ugxJIDvwM3"},{"type":"tableRow","position":{"start":{"line":69,"column":1},"end":{"line":69,"column":1}},"children":[{"type":"tableCell","align":"center","position":{"start":{"line":69,"column":1},"end":{"line":69,"column":1}},"children":[{"type":"text","value":"aimd-from-PBE-1000-npt","position":{"start":{"line":69,"column":1},"end":{"line":69,"column":1}},"key":"zJ7Kb2yO2p"}],"key":"AquDHw0Dpd"},{"type":"tableCell","align":"center","position":{"start":{"line":69,"column":1},"end":{"line":69,"column":1}},"children":[{"type":"text","value":"212,737","position":{"start":{"line":69,"column":1},"end":{"line":69,"column":1}},"key":"AcBPJ732EU"}],"key":"HIfS0I5UpL"},{"type":"tableCell","align":"center","position":{"start":{"line":69,"column":1},"end":{"line":69,"column":1}},"children":[{"type":"text","value":"261 MB","position":{"start":{"line":69,"column":1},"end":{"line":69,"column":1}},"key":"YVwKMBANDU"}],"key":"kQa25kXlax"},{"type":"tableCell","align":"right","position":{"start":{"line":69,"column":1},"end":{"line":69,"column":1}},"children":[{"type":"link","url":"https://dl.fbaipublicfiles.com/opencatalystproject/data/omat/241220/omat/val/aimd-from-PBE-1000-npt.tar.gz","position":{"start":{"line":69,"column":1},"end":{"line":69,"column":1}},"children":[{"type":"text","value":"aimd​-from​-PBE​-1000​-npt​.tar​.gz","position":{"start":{"line":69,"column":1},"end":{"line":69,"column":1}},"key":"h0ZDLUhZB1"}],"urlSource":"https://dl.fbaipublicfiles.com/opencatalystproject/data/omat/241220/omat/val/aimd-from-PBE-1000-npt.tar.gz","key":"pHsqVLQKyL"}],"key":"Pk0IUTORxl"}],"key":"BkNqeoULGC"},{"type":"tableRow","position":{"start":{"line":70,"column":1},"end":{"line":70,"column":1}},"children":[{"type":"tableCell","align":"center","position":{"start":{"line":70,"column":1},"end":{"line":70,"column":1}},"children":[{"type":"text","value":"aimd-from-PBE-1000-nvt","position":{"start":{"line":70,"column":1},"end":{"line":70,"column":1}},"key":"mCXRZjQn5d"}],"key":"Sk3WWB4KeF"},{"type":"tableCell","align":"center","position":{"start":{"line":70,"column":1},"end":{"line":70,"column":1}},"children":[{"type":"text","value":"205,165","position":{"start":{"line":70,"column":1},"end":{"line":70,"column":1}},"key":"Ob8RbSnAJt"}],"key":"Vkr8pusv7c"},{"type":"tableCell","align":"center","position":{"start":{"line":70,"column":1},"end":{"line":70,"column":1}},"children":[{"type":"text","value":"251 MB","position":{"start":{"line":70,"column":1},"end":{"line":70,"column":1}},"key":"p9jEqnwZE8"}],"key":"kCfUP3HGP8"},{"type":"tableCell","align":"right","position":{"start":{"line":70,"column":1},"end":{"line":70,"column":1}},"children":[{"type":"link","url":"https://dl.fbaipublicfiles.com/opencatalystproject/data/omat/241220/omat/val/aimd-from-PBE-1000-nvt.tar.gz","position":{"start":{"line":70,"column":1},"end":{"line":70,"column":1}},"children":[{"type":"text","value":"aimd​-from​-PBE​-1000​-nvt​.tar​.gz","position":{"start":{"line":70,"column":1},"end":{"line":70,"column":1}},"key":"s0yUrbAlNt"}],"urlSource":"https://dl.fbaipublicfiles.com/opencatalystproject/data/omat/241220/omat/val/aimd-from-PBE-1000-nvt.tar.gz","key":"UpeyAZR8cZ"}],"key":"Ds2KltZfPg"}],"key":"A6FfmCTtVq"},{"type":"tableRow","position":{"start":{"line":71,"column":1},"end":{"line":71,"column":1}},"children":[{"type":"tableCell","align":"center","position":{"start":{"line":71,"column":1},"end":{"line":71,"column":1}},"children":[{"type":"text","value":"aimd-from-PBE-3000-npt","position":{"start":{"line":71,"column":1},"end":{"line":71,"column":1}},"key":"A1EytRaf52"}],"key":"jbKJPjOmdt"},{"type":"tableCell","align":"center","position":{"start":{"line":71,"column":1},"end":{"line":71,"column":1}},"children":[{"type":"text","value":"62,130","position":{"start":{"line":71,"column":1},"end":{"line":71,"column":1}},"key":"NCiUYqrwg2"}],"key":"eJbZz9MVrY"},{"type":"tableCell","align":"center","position":{"start":{"line":71,"column":1},"end":{"line":71,"column":1}},"children":[{"type":"text","value":"282 MB","position":{"start":{"line":71,"column":1},"end":{"line":71,"column":1}},"key":"QMsKEH0Y1R"}],"key":"PTj2WTOKwp"},{"type":"tableCell","align":"right","position":{"start":{"line":71,"column":1},"end":{"line":71,"column":1}},"children":[{"type":"link","url":"https://dl.fbaipublicfiles.com/opencatalystproject/data/omat/241220/omat/val/aimd-from-PBE-3000-npt.tar.gz","position":{"start":{"line":71,"column":1},"end":{"line":71,"column":1}},"children":[{"type":"text","value":"aimd​-from​-PBE​-3000​-npt​.tar​.gz","position":{"start":{"line":71,"column":1},"end":{"line":71,"column":1}},"key":"DhKLTIHYFw"}],"urlSource":"https://dl.fbaipublicfiles.com/opencatalystproject/data/omat/241220/omat/val/aimd-from-PBE-3000-npt.tar.gz","key":"ht9TlE1u4d"}],"key":"b2D4egyT0y"}],"key":"nkSKq9rx73"},{"type":"tableRow","position":{"start":{"line":72,"column":1},"end":{"line":72,"column":1}},"children":[{"type":"tableCell","align":"center","position":{"start":{"line":72,"column":1},"end":{"line":72,"column":1}},"children":[{"type":"text","value":"aimd-from-PBE-3000-nvt","position":{"start":{"line":72,"column":1},"end":{"line":72,"column":1}},"key":"W2umADPW7K"}],"key":"Ocs3tfua4a"},{"type":"tableCell","align":"center","position":{"start":{"line":72,"column":1},"end":{"line":72,"column":1}},"children":[{"type":"text","value":"79,977","position":{"start":{"line":72,"column":1},"end":{"line":72,"column":1}},"key":"bEm4cg5AeK"}],"key":"JAYdHKnDko"},{"type":"tableCell","align":"center","position":{"start":{"line":72,"column":1},"end":{"line":72,"column":1}},"children":[{"type":"text","value":"364 MB","position":{"start":{"line":72,"column":1},"end":{"line":72,"column":1}},"key":"IoQwjkoTYr"}],"key":"gu7Gt3rNeY"},{"type":"tableCell","align":"right","position":{"start":{"line":72,"column":1},"end":{"line":72,"column":1}},"children":[{"type":"link","url":"https://dl.fbaipublicfiles.com/opencatalystproject/data/omat/241220/omat/val/aimd-from-PBE-3000-nvt.tar.gz","position":{"start":{"line":72,"column":1},"end":{"line":72,"column":1}},"children":[{"type":"text","value":"aimd​-from​-PBE​-3000​-nvt​.tar​.gz","position":{"start":{"line":72,"column":1},"end":{"line":72,"column":1}},"key":"p3sSNSWfUq"}],"urlSource":"https://dl.fbaipublicfiles.com/opencatalystproject/data/omat/241220/omat/val/aimd-from-PBE-3000-nvt.tar.gz","key":"gBhUrwHAB2"}],"key":"GXKJiJjaF6"}],"key":"QZt5jhgimu"},{"type":"tableRow","position":{"start":{"line":73,"column":1},"end":{"line":73,"column":1}},"children":[{"type":"tableCell","align":"center","position":{"start":{"line":73,"column":1},"end":{"line":73,"column":1}},"children":[{"type":"text","value":"rattled-relax","position":{"start":{"line":73,"column":1},"end":{"line":73,"column":1}},"key":"ZVzXduMVXB"}],"key":"cnz1sWBKML"},{"type":"tableCell","align":"center","position":{"start":{"line":73,"column":1},"end":{"line":73,"column":1}},"children":[{"type":"text","value":"95,206","position":{"start":{"line":73,"column":1},"end":{"line":73,"column":1}},"key":"jTTTmP3GNg"}],"key":"N02JWRpwrK"},{"type":"tableCell","align":"center","position":{"start":{"line":73,"column":1},"end":{"line":73,"column":1}},"children":[{"type":"text","value":"118 MB","position":{"start":{"line":73,"column":1},"end":{"line":73,"column":1}},"key":"Tg4zh1r8Op"}],"key":"Ed5hEJGDiL"},{"type":"tableCell","align":"right","position":{"start":{"line":73,"column":1},"end":{"line":73,"column":1}},"children":[{"type":"link","url":"https://dl.fbaipublicfiles.com/opencatalystproject/data/omat/241220/omat/val/rattled-relax.tar.gz","position":{"start":{"line":73,"column":1},"end":{"line":73,"column":1}},"children":[{"type":"text","value":"rattled​-relax​.tar​.gz","position":{"start":{"line":73,"column":1},"end":{"line":73,"column":1}},"key":"nnxdeMDvE8"}],"urlSource":"https://dl.fbaipublicfiles.com/opencatalystproject/data/omat/241220/omat/val/rattled-relax.tar.gz","key":"NhTuCiGazy"}],"key":"R4jzxsbDcS"}],"key":"hjfWMILNLI"},{"type":"tableRow","position":{"start":{"line":74,"column":1},"end":{"line":74,"column":1}},"children":[{"type":"tableCell","align":"center","position":{"start":{"line":74,"column":1},"end":{"line":74,"column":1}},"children":[{"type":"text","value":"Total","position":{"start":{"line":74,"column":1},"end":{"line":74,"column":1}},"key":"eK7fuCJzn2"}],"key":"iWnmB92232"},{"type":"tableCell","align":"center","position":{"start":{"line":74,"column":1},"end":{"line":74,"column":1}},"children":[{"type":"text","value":"1,025,361","position":{"start":{"line":74,"column":1},"end":{"line":74,"column":1}},"key":"orCF321Eob"}],"key":"IzLguCVoLh"},{"type":"tableCell","align":"center","position":{"start":{"line":74,"column":1},"end":{"line":74,"column":1}},"children":[{"type":"text","value":"1.98 GB","position":{"start":{"line":74,"column":1},"end":{"line":74,"column":1}},"key":"TEbupGISab"}],"key":"DjGOeVWIDC"},{"type":"tableCell","align":"right","position":{"start":{"line":74,"column":1},"end":{"line":74,"column":1}},"children":[],"key":"RQvWJLw6zG"}],"key":"doZbaP0dHL"}],"key":"mnMKJk5RFM"},{"type":"heading","depth":3,"position":{"start":{"line":77,"column":1},"end":{"line":77,"column":1}},"children":[{"type":"text","value":"sAlex Dataset","position":{"start":{"line":77,"column":1},"end":{"line":77,"column":1}},"key":"SvTk4ejOqj"}],"identifier":"salex-dataset","label":"sAlex Dataset","html_id":"salex-dataset","implicit":true,"key":"iyMbPj1M6Z"},{"type":"paragraph","position":{"start":{"line":78,"column":1},"end":{"line":80,"column":1}},"children":[{"type":"text","value":"We also provide the sAlex dataset used for fine-tuning of our OMat models. sAlex is a subsampled, Matbench-Discovery compliant, version of the original ","position":{"start":{"line":78,"column":1},"end":{"line":78,"column":1}},"key":"RgxlaOz7pR"},{"type":"link","url":"https://alexandria.icams.rub.de/","position":{"start":{"line":78,"column":1},"end":{"line":78,"column":1}},"children":[{"type":"text","value":"Alexandria","position":{"start":{"line":78,"column":1},"end":{"line":78,"column":1}},"key":"HZbzTTuD2V"}],"urlSource":"https://alexandria.icams.rub.de/","key":"LAwnPHLU1K"},{"type":"text","value":".\nsAlex was created by removing structures matched in WBM and only sampling structure along a trajectory with an energy difference greater than 10 meV/atom. For full details,\nplease see the manuscript.","position":{"start":{"line":78,"column":1},"end":{"line":78,"column":1}},"key":"xFTZhMEIiZ"}],"key":"DrpyLwepDs"},{"type":"table","position":{"start":{"line":82,"column":1},"end":{"line":85,"column":1}},"children":[{"type":"tableRow","position":{"start":{"line":82,"column":1},"end":{"line":82,"column":1}},"children":[{"type":"tableCell","header":true,"align":"center","position":{"start":{"line":82,"column":1},"end":{"line":82,"column":1}},"children":[{"type":"text","value":"Dataset","position":{"start":{"line":82,"column":1},"end":{"line":82,"column":1}},"key":"pszA3UNLLl"}],"key":"Oguopa2hJr"},{"type":"tableCell","header":true,"align":"center","position":{"start":{"line":82,"column":1},"end":{"line":82,"column":1}},"children":[{"type":"text","value":"Split","position":{"start":{"line":82,"column":1},"end":{"line":82,"column":1}},"key":"WmDqwJcr9D"}],"key":"roKOZ4h3ku"},{"type":"tableCell","header":true,"align":"center","position":{"start":{"line":82,"column":1},"end":{"line":82,"column":1}},"children":[{"type":"text","value":"No. Structures","position":{"start":{"line":82,"column":1},"end":{"line":82,"column":1}},"key":"l4Y0u68yA9"}],"key":"FXpGsjIDm6"},{"type":"tableCell","header":true,"align":"center","position":{"start":{"line":82,"column":1},"end":{"line":82,"column":1}},"children":[{"type":"text","value":"File Size","position":{"start":{"line":82,"column":1},"end":{"line":82,"column":1}},"key":"TFSv80tHCQ"}],"key":"qXcx7SwotS"},{"type":"tableCell","header":true,"align":"right","position":{"start":{"line":82,"column":1},"end":{"line":82,"column":1}},"children":[{"type":"text","value":"Download","position":{"start":{"line":82,"column":1},"end":{"line":82,"column":1}},"key":"abNTe8ZSWa"}],"key":"Di7kknzXB8"}],"key":"ADtmnQfHbM"},{"type":"tableRow","position":{"start":{"line":84,"column":1},"end":{"line":84,"column":1}},"children":[{"type":"tableCell","align":"center","position":{"start":{"line":84,"column":1},"end":{"line":84,"column":1}},"children":[{"type":"text","value":"sAlex","position":{"start":{"line":84,"column":1},"end":{"line":84,"column":1}},"key":"vBbPzrLiuc"}],"key":"ylmiohXJ7a"},{"type":"tableCell","align":"center","position":{"start":{"line":84,"column":1},"end":{"line":84,"column":1}},"children":[{"type":"text","value":"train","position":{"start":{"line":84,"column":1},"end":{"line":84,"column":1}},"key":"CS8iyi6tOL"}],"key":"aS0NxasOn0"},{"type":"tableCell","align":"center","position":{"start":{"line":84,"column":1},"end":{"line":84,"column":1}},"children":[{"type":"text","value":"10,447,765","position":{"start":{"line":84,"column":1},"end":{"line":84,"column":1}},"key":"KzEeeqE3hK"}],"key":"HpX6fPkIrd"},{"type":"tableCell","align":"center","position":{"start":{"line":84,"column":1},"end":{"line":84,"column":1}},"children":[{"type":"text","value":"7.6 GB","position":{"start":{"line":84,"column":1},"end":{"line":84,"column":1}},"key":"OruO2WT1NR"}],"key":"JlbvF5Q91y"},{"type":"tableCell","align":"right","position":{"start":{"line":84,"column":1},"end":{"line":84,"column":1}},"children":[{"type":"link","url":"https://dl.fbaipublicfiles.com/opencatalystproject/data/omat/241018/sAlex/train.tar.gz","position":{"start":{"line":84,"column":1},"end":{"line":84,"column":1}},"children":[{"type":"text","value":"train.tar.gz","position":{"start":{"line":84,"column":1},"end":{"line":84,"column":1}},"key":"qvE1qhBaco"}],"urlSource":"https://dl.fbaipublicfiles.com/opencatalystproject/data/omat/241018/sAlex/train.tar.gz","key":"gTsTok55LC"}],"key":"LUIAWP1uJ5"}],"key":"UszX1gK6bN"},{"type":"tableRow","position":{"start":{"line":85,"column":1},"end":{"line":85,"column":1}},"children":[{"type":"tableCell","align":"center","position":{"start":{"line":85,"column":1},"end":{"line":85,"column":1}},"children":[{"type":"text","value":"sAlex","position":{"start":{"line":85,"column":1},"end":{"line":85,"column":1}},"key":"VPWerEWNJN"}],"key":"srlrEfhhfZ"},{"type":"tableCell","align":"center","position":{"start":{"line":85,"column":1},"end":{"line":85,"column":1}},"children":[{"type":"text","value":"val","position":{"start":{"line":85,"column":1},"end":{"line":85,"column":1}},"key":"fMSLExMn8E"}],"key":"r4UYTGNNgx"},{"type":"tableCell","align":"center","position":{"start":{"line":85,"column":1},"end":{"line":85,"column":1}},"children":[{"type":"text","value":"553,218","position":{"start":{"line":85,"column":1},"end":{"line":85,"column":1}},"key":"kU501PPVGu"}],"key":"MSVIiPJkrE"},{"type":"tableCell","align":"center","position":{"start":{"line":85,"column":1},"end":{"line":85,"column":1}},"children":[{"type":"text","value":"408 MB","position":{"start":{"line":85,"column":1},"end":{"line":85,"column":1}},"key":"uJosTHqC6A"}],"key":"zWDpmkuA7H"},{"type":"tableCell","align":"right","position":{"start":{"line":85,"column":1},"end":{"line":85,"column":1}},"children":[{"type":"link","url":"https://dl.fbaipublicfiles.com/opencatalystproject/data/omat/241018/sAlex/val.tar.gz","position":{"start":{"line":85,"column":1},"end":{"line":85,"column":1}},"children":[{"type":"text","value":"val.tar.gz","position":{"start":{"line":85,"column":1},"end":{"line":85,"column":1}},"key":"Ri2uw6MD78"}],"urlSource":"https://dl.fbaipublicfiles.com/opencatalystproject/data/omat/241018/sAlex/val.tar.gz","key":"xhMWBIUG5K"}],"key":"rMsyqtgMgW"}],"key":"gitdoSt7GI"}],"key":"xZvDuGFu4H"},{"type":"heading","depth":2,"position":{"start":{"line":88,"column":1},"end":{"line":88,"column":1}},"children":[{"type":"text","value":"Getting ASE atoms objects","position":{"start":{"line":88,"column":1},"end":{"line":88,"column":1}},"key":"TgWe7bylTM"}],"identifier":"getting-ase-atoms-objects","label":"Getting ASE atoms objects","html_id":"getting-ase-atoms-objects","implicit":true,"key":"Jm4eiuGJEi"},{"type":"paragraph","position":{"start":{"line":89,"column":1},"end":{"line":90,"column":1}},"children":[{"type":"text","value":"Dataset files are written as ","position":{"start":{"line":89,"column":1},"end":{"line":89,"column":1}},"key":"xR2Qday5pO"},{"type":"inlineCode","value":"AseLMDBDatabase","position":{"start":{"line":89,"column":1},"end":{"line":89,"column":1}},"key":"eoHKS6sjmA"},{"type":"text","value":" objects which are an implementation of an ","position":{"start":{"line":89,"column":1},"end":{"line":89,"column":1}},"key":"Sg9CjL2NeT"},{"type":"link","url":"https://wiki.fysik.dtu.dk/ase/ase/db/db.html","position":{"start":{"line":89,"column":1},"end":{"line":89,"column":1}},"children":[{"type":"text","value":"ASE Database","position":{"start":{"line":89,"column":1},"end":{"line":89,"column":1}},"key":"FwSOEBzNjN"}],"urlSource":"https://wiki.fysik.dtu.dk/ase/ase/db/db.html","key":"FC30nUQakz"},{"type":"text","value":",\nin LMDB format. A single *","position":{"start":{"line":89,"column":1},"end":{"line":89,"column":1}},"key":"jjiGaDZkNW"},{"type":"emphasis","position":{"start":{"line":89,"column":1},"end":{"line":89,"column":1}},"children":[{"type":"text","value":".aselmdb","position":{"start":{"line":89,"column":1},"end":{"line":89,"column":1}},"key":"GvGAVNjzie"}],"key":"naLcbFGOWo"},{"type":"text","value":" file can be read and queried like any other ASE DB.","position":{"start":{"line":89,"column":1},"end":{"line":89,"column":1}},"key":"dSPe348x3s"}],"key":"DpxabSqfvj"},{"type":"paragraph","position":{"start":{"line":92,"column":1},"end":{"line":92,"column":1}},"children":[{"type":"text","value":"You can also read many DB files at once and access atoms objects using the ","position":{"start":{"line":92,"column":1},"end":{"line":92,"column":1}},"key":"lXFZvbL5Gw"},{"type":"inlineCode","value":"AseDBDataset","position":{"start":{"line":92,"column":1},"end":{"line":92,"column":1}},"key":"qq69QU1jGt"},{"type":"text","value":" class.","position":{"start":{"line":92,"column":1},"end":{"line":92,"column":1}},"key":"WWwp9d5Zmo"}],"key":"Aso8tVFXeD"},{"type":"paragraph","position":{"start":{"line":94,"column":1},"end":{"line":94,"column":1}},"children":[{"type":"text","value":"For example to read the ","position":{"start":{"line":94,"column":1},"end":{"line":94,"column":1}},"key":"PUrOJ0JO1d"},{"type":"strong","position":{"start":{"line":94,"column":1},"end":{"line":94,"column":1}},"children":[{"type":"text","value":"rattled-relax","position":{"start":{"line":94,"column":1},"end":{"line":94,"column":1}},"key":"iZIcXJnH12"}],"key":"e5BmNAxPRV"},{"type":"text","value":" subdataset,","position":{"start":{"line":94,"column":1},"end":{"line":94,"column":1}},"key":"ZCSgHpTruw"}],"key":"G2jmh9bevx"},{"type":"code","lang":"python","value":"from fairchem.core.datasets import AseDBDataset\n\ndataset_path = \"/path/to/omat24/train/rattled-relax\"\nconfig_kwargs = {}  # see tutorial on additiona configuration\n\ndataset = AseDBDataset(config=dict(src=dataset_path, **config_kwargs))\n\n# atoms objects can be retrieved by index\natoms = dataset.get_atoms(0)","position":{"start":{"line":95,"column":1},"end":{"line":105,"column":1}},"key":"p9LNthEcr4"},{"type":"paragraph","position":{"start":{"line":107,"column":1},"end":{"line":107,"column":1}},"children":[{"type":"text","value":"To read more than one subdataset you can simply pass a list of subdataset paths,","position":{"start":{"line":107,"column":1},"end":{"line":107,"column":1}},"key":"BPLS0yREfz"}],"key":"P3QWwY1giR"},{"type":"code","lang":"python","value":"from fairchem.core.datasets import AseDBDataset\n\nconfig_kwargs = {}  # see tutorial on additiona configuration\ndataset_paths = [\n    \"/path/to/omat24/train/rattled-relax\",\n    \"/path/to/omat24/train/rattled-1000-subsampled\",\n    \"/path/to/omat24/train/rattled-1000\",\n]\ndataset = AseDBDataset(config=dict(src=dataset_paths, **config_kwargs))","position":{"start":{"line":108,"column":1},"end":{"line":118,"column":1}},"key":"b9EAl5uM7p"},{"type":"paragraph","position":{"start":{"line":119,"column":1},"end":{"line":119,"column":1}},"children":[{"type":"text","value":"To read all of the OMat24 training or validations splits simply pass the paths to all subdatasets.","position":{"start":{"line":119,"column":1},"end":{"line":119,"column":1}},"key":"quQLGSTC3X"}],"key":"Xzea6TB3SC"},{"type":"heading","depth":3,"position":{"start":{"line":121,"column":1},"end":{"line":121,"column":1}},"children":[{"type":"text","value":"Citing OMat24","position":{"start":{"line":121,"column":1},"end":{"line":121,"column":1}},"key":"PZxTVoC7Kj"}],"identifier":"citing-omat24","label":"Citing OMat24","html_id":"citing-omat24","implicit":true,"key":"dfr4tm8oiV"},{"type":"paragraph","position":{"start":{"line":123,"column":1},"end":{"line":123,"column":1}},"children":[{"type":"text","value":"The OMat24 dataset is licensed under a ","position":{"start":{"line":123,"column":1},"end":{"line":123,"column":1}},"key":"COxKBZYrC8"},{"type":"link","url":"https://creativecommons.org/licenses/by/4.0/legalcode","position":{"start":{"line":123,"column":1},"end":{"line":123,"column":1}},"children":[{"type":"text","value":"Creative Commons Attribution 4.0 License","position":{"start":{"line":123,"column":1},"end":{"line":123,"column":1}},"key":"bbYM2grIIu"}],"urlSource":"https://creativecommons.org/licenses/by/4.0/legalcode","key":"gwbOtwAX8j"},{"type":"text","value":".","position":{"start":{"line":123,"column":1},"end":{"line":123,"column":1}},"key":"Wx4rIhat3g"}],"key":"JFRIOyjaSY"},{"type":"paragraph","position":{"start":{"line":125,"column":1},"end":{"line":125,"column":1}},"children":[{"type":"text","value":"Please consider citing the following paper in any publications that uses this dataset:","position":{"start":{"line":125,"column":1},"end":{"line":125,"column":1}},"key":"q1a4nrh0gj"}],"key":"alDjCsKCQ4"},{"type":"code","lang":"bib","value":"@article{barroso_omat24,\n  title={Open Materials 2024 (OMat24) Inorganic Materials Dataset and Models},\n  author={Barroso-Luque, Luis and Muhammed, Shuaibi and Fu, Xiang and Wood, Brandon, Dzamba, Misko, and Gao, Meng and Rizvi, Ammar and  Zitnick, C. Lawrence and Ulissi, Zachary W.},\n  journal={arXiv preprint arXiv:2410.12771},\n  year={2024}\n}\n@article{schmidt_2023_machine,\n  title={Machine-Learning-Assisted Determination of the Global Zero-Temperature Phase Diagram of Materials},\n  author={Schmidt, Jonathan and Hoffmann, Noah and Wang, Hai-Chen and Borlido, Pedro and Carri{\\c{c}}o, Pedro JMA and Cerqueira, Tiago FT and Botti, Silvana and Marques, Miguel AL},\n  journal={Advanced Materials},\n  volume={35},\n  number={22},\n  pages={2210788},\n  year={2023},\n  url={https://onlinelibrary.wiley.com/doi/full/10.1002/adma.202210788},\n  publisher={Wiley Online Library}\n}","position":{"start":{"line":128,"column":1},"end":{"line":146,"column":1}},"key":"m1L9fyEmao"}],"key":"o9BIM3AkV2"}],"key":"bS6L8Za1TC"},"references":{"cite":{"order":[],"data":{}}},"footer":{"navigation":{"prev":{"title":"Datasets","url":"/summary-6","group":"Inorganic Materials"},"next":{"title":"Pretrained models","url":"/models-2","group":"Inorganic Materials"}}},"domain":"http://localhost:3000"}